{
  "title": "Juízes 15",
  "book_name": "Juízes",
  "book_slug": "juízes",
  "chapter_number": 15,
  "introduction": "<p class=\"wp-block-paragraph\"><a href=\"https://www.die-bibel.de/en/bible/BHS/JDG.15\" rel=\"noreferrer noopener\" target=\"_blank\">Juízes 15 na <em>Biblia Hebraica Stuttgartensia</em></a></p>\n<p class=\"wp-block-paragraph\"><a href=\"https://www.youtube.com/watch?v=HkFeO_CTJ74\" rel=\"noreferrer noopener\" target=\"_blank\">Comentário a Juízes 15,1-6</a></p>\n<p class=\"wp-block-paragraph\"><a href=\"https://www.youtube.com/watch?v=4DmtPkdQxRA\" rel=\"noreferrer noopener\" target=\"_blank\">Comentário a Juízes 15,7-13</a></p>\n<p class=\"wp-block-paragraph\"><a href=\"https://www.youtube.com/watch?v=KcPjlK83io8\" rel=\"noreferrer noopener\" target=\"_blank\">Comentário a Juízes 15,14-20</a></p>",
  "verses": [
    {
      "number": 1,
      "text": "E está. Desde dias. Em dias de colheita de trigo. E visita Shimshon. A mulher dele. Em cabrito de cabras. E diz ele. Vou eu. À mulher de mim. Para a câmara. E não dá ele. O pai dela. Para ir.",
      "lines": [
        {
          "line_index": 0,
          "text": "E está.",
          "raw_html": "<p class=\"wp-block-paragraph\"> E está<a name=\"rf1-20399\"></a><sup><a href=\"#fn1-20399\" rel=\"footnote\" title=\"Clique para ir para a nota de rodapé 1\">1</a></sup><a name=\"rf2-20399\"></a><sup><a href=\"#fn2-20399\" rel=\"footnote\" title=\"Clique para ir para a nota de rodapé 2\">2</a></sup>.</p>"
        },
        {
          "line_index": 1,
          "text": "Desde dias.",
          "raw_html": "<p class=\"wp-block-paragraph\">Desde dias.</p>"
        },
        {
          "line_index": 2,
          "text": "Em dias de colheita de trigo.",
          "raw_html": "<p class=\"wp-block-paragraph\">Em dias de colheita de trigo.</p>"
        },
        {
          "line_index": 3,
          "text": "E visita Shimshon.",
          "raw_html": "<p class=\"wp-block-paragraph\">E visita<a name=\"rf3-20399\"></a><sup><a href=\"#fn3-20399\" rel=\"footnote\" title=\"Clique para ir para a nota de rodapé 3\">3</a></sup> Shimshon.</p>"
        },
        {
          "line_index": 4,
          "text": "A mulher dele.",
          "raw_html": "<p class=\"wp-block-paragraph\">A mulher dele.</p>"
        },
        {
          "line_index": 5,
          "text": "Em cabrito de cabras.",
          "raw_html": "<p class=\"wp-block-paragraph\">Em cabrito de cabras<a name=\"rf4-20399\"></a><sup><a href=\"#fn4-20399\" rel=\"footnote\" title=\"Clique para ir para a nota de rodapé 4\">4</a></sup>.</p>"
        },
        {
          "line_index": 6,
          "text": "E diz ele.",
          "raw_html": "<p class=\"wp-block-paragraph\">E diz ele.</p>"
        },
        {
          "line_index": 7,
          "text": "Vou eu.",
          "raw_html": "<p class=\"wp-block-paragraph\">Vou eu<a name=\"rf5-20399\"></a><sup><a href=\"#fn5-20399\" rel=\"footnote\" title=\"Clique para ir para a nota de rodapé 5\">5</a></sup>.</p>"
        },
        {
          "line_index": 8,
          "text": "À mulher de mim.",
          "raw_html": "<p class=\"wp-block-paragraph\">À mulher de mim.</p>"
        },
        {
          "line_index": 9,
          "text": "Para a câmara.",
          "raw_html": "<p class=\"wp-block-paragraph\">Para a câmara.</p>"
        },
        {
          "line_index": 10,
          "text": "E não dá ele.",
          "raw_html": "<p class=\"wp-block-paragraph\">E não dá ele.</p>"
        },
        {
          "line_index": 11,
          "text": "O pai dela.",
          "raw_html": "<p class=\"wp-block-paragraph\">O pai dela.</p>"
        },
        {
          "line_index": 12,
          "text": "Para ir.",
          "raw_html": "<p class=\"wp-block-paragraph\">Para ir<a name=\"rf6-20399\"></a><sup><a href=\"#fn6-20399\" rel=\"footnote\" title=\"Clique para ir para a nota de rodapé 6\">6</a></sup>.</p>"
        }
      ]
    },
    {
      "number": 2,
      "text": "E diz. O pai dela. Dizer. Digo eu. Que odiar odeias tu ela. E dou eu ela. Para o camarada de ti. Acaso não. A irmã dela. A pequena. Boa desde ela? Está ela. Favor. Para ti. Debaixo dela.",
      "lines": [
        {
          "line_index": 0,
          "text": "E diz.",
          "raw_html": "<p class=\"wp-block-paragraph\"> E diz.</p>"
        },
        {
          "line_index": 1,
          "text": "O pai dela.",
          "raw_html": "<p class=\"wp-block-paragraph\">O pai dela.</p>"
        },
        {
          "line_index": 2,
          "text": "Dizer.",
          "raw_html": "<p class=\"wp-block-paragraph\">Dizer.</p>"
        },
        {
          "line_index": 3,
          "text": "Digo eu.",
          "raw_html": "<p class=\"wp-block-paragraph\">Digo eu.</p>"
        },
        {
          "line_index": 4,
          "text": "Que odiar odeias tu ela.",
          "raw_html": "<p class=\"wp-block-paragraph\">Que odiar odeias tu ela.</p>"
        },
        {
          "line_index": 5,
          "text": "E dou eu ela.",
          "raw_html": "<p class=\"wp-block-paragraph\">E dou eu ela.</p>"
        },
        {
          "line_index": 6,
          "text": "Para o camarada de ti.",
          "raw_html": "<p class=\"wp-block-paragraph\">Para o camarada de ti.</p>"
        },
        {
          "line_index": 7,
          "text": "Acaso não.",
          "raw_html": "<p class=\"wp-block-paragraph\">Acaso não.</p>"
        },
        {
          "line_index": 8,
          "text": "A irmã dela.",
          "raw_html": "<p class=\"wp-block-paragraph\">A irmã dela<a name=\"rf7-20399\"></a><sup><a href=\"#fn7-20399\" rel=\"footnote\" title=\"Clique para ir para a nota de rodapé 7\">7</a></sup>.</p>"
        },
        {
          "line_index": 9,
          "text": "A pequena.",
          "raw_html": "<p class=\"wp-block-paragraph\">A pequena.</p>"
        },
        {
          "line_index": 10,
          "text": "Boa desde ela?",
          "raw_html": "<p class=\"wp-block-paragraph\">Boa desde ela?</p>"
        },
        {
          "line_index": 11,
          "text": "Está ela.",
          "raw_html": "<p class=\"wp-block-paragraph\">Está ela<a name=\"rf8-20399\"></a><sup><a href=\"#fn8-20399\" rel=\"footnote\" title=\"Clique para ir para a nota de rodapé 8\">8</a></sup>.</p>"
        },
        {
          "line_index": 12,
          "text": "Favor.",
          "raw_html": "<p class=\"wp-block-paragraph\">Favor.</p>"
        },
        {
          "line_index": 13,
          "text": "Para ti.",
          "raw_html": "<p class=\"wp-block-paragraph\">Para ti.</p>"
        },
        {
          "line_index": 14,
          "text": "Debaixo dela.",
          "raw_html": "<p class=\"wp-block-paragraph\">Debaixo dela<a name=\"rf9-20399\"></a><sup><a href=\"#fn9-20399\" rel=\"footnote\" title=\"Clique para ir para a nota de rodapé 9\">9</a></sup>.</p>"
        }
      ]
    },
    {
      "number": 3,
      "text": "E diz para eles Shimshon. Livrado estou eu. A passada. Desde pelishtim. Que fazedor eu. Com eles. Maldade.",
      "lines": [
        {
          "line_index": 0,
          "text": "E diz para eles Shimshon.",
          "raw_html": "<p class=\"wp-block-paragraph\">E diz para eles Shimshon.</p>"
        },
        {
          "line_index": 1,
          "text": "Livrado estou eu.",
          "raw_html": "<p class=\"wp-block-paragraph\">Livrado estou eu<a name=\"rf10-20399\"></a><sup><a href=\"#fn10-20399\" rel=\"footnote\" title=\"Clique para ir para a nota de rodapé 10\">10</a></sup>.</p>"
        },
        {
          "line_index": 2,
          "text": "A passada.",
          "raw_html": "<p class=\"wp-block-paragraph\">A passada.</p>"
        },
        {
          "line_index": 3,
          "text": "Desde pelishtim.",
          "raw_html": "<p class=\"wp-block-paragraph\">Desde pelishtim.</p>"
        },
        {
          "line_index": 4,
          "text": "Que fazedor eu.",
          "raw_html": "<p class=\"wp-block-paragraph\">Que fazedor eu.</p>"
        },
        {
          "line_index": 5,
          "text": "Com eles.",
          "raw_html": "<p class=\"wp-block-paragraph\">Com eles.</p>"
        },
        {
          "line_index": 6,
          "text": "Maldade.",
          "raw_html": "<p class=\"wp-block-paragraph\">Maldade<a name=\"rf11-20399\"></a><sup><a href=\"#fn11-20399\" rel=\"footnote\" title=\"Clique para ir para a nota de rodapé 11\">11</a></sup>.</p>"
        }
      ]
    },
    {
      "number": 4,
      "text": "E anda Shimshon. E captura ele. Três de centenas de raposas. E toma ele archote. E faz ele enfacear. Rabo a rabo. E coloca ele archote um. Entre os dois dos rabos. No meio.",
      "lines": [
        {
          "line_index": 0,
          "text": "E anda Shimshon.",
          "raw_html": "<p class=\"wp-block-paragraph\"> E anda Shimshon.</p>"
        },
        {
          "line_index": 1,
          "text": "E captura ele.",
          "raw_html": "<p class=\"wp-block-paragraph\">E captura ele.</p>"
        },
        {
          "line_index": 2,
          "text": "Três de centenas de raposas.",
          "raw_html": "<p class=\"wp-block-paragraph\">Três de centenas de raposas<a name=\"rf12-20399\"></a><sup><a href=\"#fn12-20399\" rel=\"footnote\" title=\"Clique para ir para a nota de rodapé 12\">12</a></sup>.</p>"
        },
        {
          "line_index": 3,
          "text": "E toma ele archote.",
          "raw_html": "<p class=\"wp-block-paragraph\">E toma ele archote.</p>"
        },
        {
          "line_index": 4,
          "text": "E faz ele enfacear.",
          "raw_html": "<p class=\"wp-block-paragraph\">E faz ele enfacear.</p>"
        },
        {
          "line_index": 5,
          "text": "Rabo a rabo.",
          "raw_html": "<p class=\"wp-block-paragraph\">Rabo a rabo.</p>"
        },
        {
          "line_index": 6,
          "text": "E coloca ele archote um.",
          "raw_html": "<p class=\"wp-block-paragraph\">E coloca ele archote um.</p>"
        },
        {
          "line_index": 7,
          "text": "Entre os dois dos rabos.",
          "raw_html": "<p class=\"wp-block-paragraph\">Entre os dois dos rabos.</p>"
        },
        {
          "line_index": 8,
          "text": "No meio.",
          "raw_html": "<p class=\"wp-block-paragraph\">No meio.</p>"
        }
      ]
    },
    {
      "number": 5,
      "text": "E faz ele queimar flama. Nas raposas. E despede ele. Nos talos pelishtim. E faz queimar ele. Desde messe. E até talo. E até vinhedo. Azeitonazeiro.",
      "lines": [
        {
          "line_index": 0,
          "text": "E faz ele queimar flama.",
          "raw_html": "<p class=\"wp-block-paragraph\"> E faz ele queimar flama.</p>"
        },
        {
          "line_index": 1,
          "text": "Nas raposas.",
          "raw_html": "<p class=\"wp-block-paragraph\">Nas raposas.</p>"
        },
        {
          "line_index": 2,
          "text": "E despede ele.",
          "raw_html": "<p class=\"wp-block-paragraph\">E despede ele<a name=\"rf13-20399\"></a><sup><a href=\"#fn13-20399\" rel=\"footnote\" title=\"Clique para ir para a nota de rodapé 13\">13</a></sup>.</p>"
        },
        {
          "line_index": 3,
          "text": "Nos talos pelishtim.",
          "raw_html": "<p class=\"wp-block-paragraph\">Nos talos pelishtim.</p>"
        },
        {
          "line_index": 4,
          "text": "E faz queimar ele.",
          "raw_html": "<p class=\"wp-block-paragraph\">E faz queimar ele.</p>"
        },
        {
          "line_index": 5,
          "text": "Desde messe.",
          "raw_html": "<p class=\"wp-block-paragraph\">Desde messe.</p>"
        },
        {
          "line_index": 6,
          "text": "E até talo.",
          "raw_html": "<p class=\"wp-block-paragraph\">E até talo.</p>"
        },
        {
          "line_index": 7,
          "text": "E até vinhedo.",
          "raw_html": "<p class=\"wp-block-paragraph\">E até vinhedo.</p>"
        },
        {
          "line_index": 8,
          "text": "Azeitonazeiro.",
          "raw_html": "<p class=\"wp-block-paragraph\">Azeitonazeiro.</p>"
        }
      ]
    },
    {
      "number": 6,
      "text": "E dizem pelishtim. Quem faz essa? E dizem eles. Shimshon. O genro do timni. Que toma ele a mulher dele. E dá ele ela. Para o camarada dele. E sobem pelishtim. E ardem eles. Ela. E o pai dela. Na flama.",
      "lines": [
        {
          "line_index": 0,
          "text": "E dizem pelishtim.",
          "raw_html": "<p class=\"wp-block-paragraph\"> E dizem pelishtim.</p>"
        },
        {
          "line_index": 1,
          "text": "Quem faz essa?",
          "raw_html": "<p class=\"wp-block-paragraph\">Quem<a name=\"rf14-20399\"></a><sup><a href=\"#fn14-20399\" rel=\"footnote\" title=\"Clique para ir para a nota de rodapé 14\">14</a></sup> faz<a name=\"rf15-20399\"></a><sup><a href=\"#fn15-20399\" rel=\"footnote\" title=\"Clique para ir para a nota de rodapé 15\">15</a></sup> essa?</p>"
        },
        {
          "line_index": 2,
          "text": "E dizem eles.",
          "raw_html": "<p class=\"wp-block-paragraph\">E dizem eles.</p>"
        },
        {
          "line_index": 3,
          "text": "Shimshon.",
          "raw_html": "<p class=\"wp-block-paragraph\">Shimshon.</p>"
        },
        {
          "line_index": 4,
          "text": "O genro do timni.",
          "raw_html": "<p class=\"wp-block-paragraph\">O genro do timni.</p>"
        },
        {
          "line_index": 5,
          "text": "Que toma ele a mulher dele.",
          "raw_html": "<p class=\"wp-block-paragraph\">Que toma ele a mulher dele.</p>"
        },
        {
          "line_index": 6,
          "text": "E dá ele ela.",
          "raw_html": "<p class=\"wp-block-paragraph\">E dá ele ela.</p>"
        },
        {
          "line_index": 7,
          "text": "Para o camarada dele.",
          "raw_html": "<p class=\"wp-block-paragraph\">Para o camarada dele.</p>"
        },
        {
          "line_index": 8,
          "text": "E sobem pelishtim.",
          "raw_html": "<p class=\"wp-block-paragraph\">E sobem<a name=\"rf16-20399\"></a><sup><a href=\"#fn16-20399\" rel=\"footnote\" title=\"Clique para ir para a nota de rodapé 16\">16</a></sup> pelishtim.</p>"
        },
        {
          "line_index": 9,
          "text": "E ardem eles.",
          "raw_html": "<p class=\"wp-block-paragraph\">E ardem eles<a name=\"rf17-20399\"></a><sup><a href=\"#fn17-20399\" rel=\"footnote\" title=\"Clique para ir para a nota de rodapé 17\">17</a></sup>.</p>"
        },
        {
          "line_index": 10,
          "text": "Ela.",
          "raw_html": "<p class=\"wp-block-paragraph\">Ela.</p>"
        },
        {
          "line_index": 11,
          "text": "E o pai dela.",
          "raw_html": "<p class=\"wp-block-paragraph\">E o pai dela.</p>"
        },
        {
          "line_index": 12,
          "text": "Na flama.",
          "raw_html": "<p class=\"wp-block-paragraph\">Na flama<a name=\"rf18-20399\"></a><sup><a href=\"#fn18-20399\" rel=\"footnote\" title=\"Clique para ir para a nota de rodapé 18\">18</a></sup>.</p>"
        }
      ]
    },
    {
      "number": 7,
      "text": "E diz para eles Shimshon. Se fazeis vós. Conforme essa. Que sim. Vingado estou eu. Em vós. E depois cesso eu.",
      "lines": [
        {
          "line_index": 0,
          "text": "E diz para eles Shimshon.",
          "raw_html": "<p class=\"wp-block-paragraph\">E diz para eles Shimshon.</p>"
        },
        {
          "line_index": 1,
          "text": "Se fazeis vós.",
          "raw_html": "<p class=\"wp-block-paragraph\">Se fazeis vós<a name=\"rf19-20399\"></a><sup><a href=\"#fn19-20399\" rel=\"footnote\" title=\"Clique para ir para a nota de rodapé 19\">19</a></sup>.</p>"
        },
        {
          "line_index": 2,
          "text": "Conforme essa.",
          "raw_html": "<p class=\"wp-block-paragraph\">Conforme essa.</p>"
        },
        {
          "line_index": 3,
          "text": "Que sim.",
          "raw_html": "<p class=\"wp-block-paragraph\">Que sim<a name=\"rf20-20399\"></a><sup><a href=\"#fn20-20399\" rel=\"footnote\" title=\"Clique para ir para a nota de rodapé 20\">20</a></sup>.</p>"
        },
        {
          "line_index": 4,
          "text": "Vingado estou eu.",
          "raw_html": "<p class=\"wp-block-paragraph\">Vingado estou eu.</p>"
        },
        {
          "line_index": 5,
          "text": "Em vós.",
          "raw_html": "<p class=\"wp-block-paragraph\">Em vós.</p>"
        },
        {
          "line_index": 6,
          "text": "E depois cesso eu.",
          "raw_html": "<p class=\"wp-block-paragraph\">E depois cesso eu.</p>"
        }
      ]
    },
    {
      "number": 8,
      "text": "E faz ele ferir. Eles. Perna sobre coxa. Calamidade grande. E desce ele. E assenta ele. Na fenda do rochedo de ‘Etam.",
      "lines": [
        {
          "line_index": 0,
          "text": "E faz ele ferir.",
          "raw_html": "<p class=\"wp-block-paragraph\"> E faz ele ferir<a name=\"rf21-20399\"></a><sup><a href=\"#fn21-20399\" rel=\"footnote\" title=\"Clique para ir para a nota de rodapé 21\">21</a></sup>.</p>"
        },
        {
          "line_index": 1,
          "text": "Eles.",
          "raw_html": "<p class=\"wp-block-paragraph\">Eles<a name=\"rf22-20399\"></a><sup><a href=\"#fn22-20399\" rel=\"footnote\" title=\"Clique para ir para a nota de rodapé 22\">22</a></sup>.</p>"
        },
        {
          "line_index": 2,
          "text": "Perna sobre coxa.",
          "raw_html": "<p class=\"wp-block-paragraph\">Perna sobre coxa.</p>"
        },
        {
          "line_index": 3,
          "text": "Calamidade grande.",
          "raw_html": "<p class=\"wp-block-paragraph\">Calamidade grande<a name=\"rf23-20399\"></a><sup><a href=\"#fn23-20399\" rel=\"footnote\" title=\"Clique para ir para a nota de rodapé 23\">23</a></sup>.</p>"
        },
        {
          "line_index": 4,
          "text": "E desce ele.",
          "raw_html": "<p class=\"wp-block-paragraph\">E desce ele.</p>"
        },
        {
          "line_index": 5,
          "text": "E assenta ele.",
          "raw_html": "<p class=\"wp-block-paragraph\">E assenta ele.</p>"
        },
        {
          "line_index": 6,
          "text": "Na fenda do rochedo de ‘Etam.",
          "raw_html": "<p class=\"wp-block-paragraph\">Na fenda do rochedo de ‘Etam.</p>"
        }
      ]
    },
    {
      "number": 9,
      "text": "E sobem pelishtim. E acampam eles. Em Yehudah. E estendidos estão eles em Lehi.",
      "lines": [
        {
          "line_index": 0,
          "text": "E sobem pelishtim.",
          "raw_html": "<p class=\"wp-block-paragraph\"> E sobem<a name=\"rf24-20399\"></a><sup><a href=\"#fn24-20399\" rel=\"footnote\" title=\"Clique para ir para a nota de rodapé 24\">24</a></sup> pelishtim.</p>"
        },
        {
          "line_index": 1,
          "text": "E acampam eles.",
          "raw_html": "<p class=\"wp-block-paragraph\">E acampam eles<a name=\"rf25-20399\"></a><sup><a href=\"#fn25-20399\" rel=\"footnote\" title=\"Clique para ir para a nota de rodapé 25\">25</a></sup>.</p>"
        },
        {
          "line_index": 2,
          "text": "Em Yehudah.",
          "raw_html": "<p class=\"wp-block-paragraph\">Em Yehudah.</p>"
        },
        {
          "line_index": 3,
          "text": "E estendidos estão eles em Lehi.",
          "raw_html": "<p class=\"wp-block-paragraph\">E estendidos estão eles em Lehi.</p>"
        }
      ]
    },
    {
      "number": 10,
      "text": "E dizem eles. O homem de Yehudah. Para qual. Subis vós. Sobre nós? E dizem eles. Para prender Shimshon. Subimos nós. Para fazer. Para ele. Conforme que faz ele. Para nós.",
      "lines": [
        {
          "line_index": 0,
          "text": "E dizem eles.",
          "raw_html": "<p class=\"wp-block-paragraph\"> E dizem eles.</p>"
        },
        {
          "line_index": 1,
          "text": "O homem de Yehudah.",
          "raw_html": "<p class=\"wp-block-paragraph\">O homem de Yehudah.</p>"
        },
        {
          "line_index": 2,
          "text": "Para qual.",
          "raw_html": "<p class=\"wp-block-paragraph\">Para qual.</p>"
        },
        {
          "line_index": 3,
          "text": "Subis vós.",
          "raw_html": "<p class=\"wp-block-paragraph\">Subis vós<a name=\"rf26-20399\"></a><sup><a href=\"#fn26-20399\" rel=\"footnote\" title=\"Clique para ir para a nota de rodapé 26\">26</a></sup>.</p>"
        },
        {
          "line_index": 4,
          "text": "Sobre nós?",
          "raw_html": "<p class=\"wp-block-paragraph\">Sobre nós?</p>"
        },
        {
          "line_index": 5,
          "text": "E dizem eles.",
          "raw_html": "<p class=\"wp-block-paragraph\">E dizem eles.</p>"
        },
        {
          "line_index": 6,
          "text": "Para prender Shimshon.",
          "raw_html": "<p class=\"wp-block-paragraph\">Para prender Shimshon.</p>"
        },
        {
          "line_index": 7,
          "text": "Subimos nós.",
          "raw_html": "<p class=\"wp-block-paragraph\">Subimos nós<a name=\"rf27-20399\"></a><sup><a href=\"#fn27-20399\" rel=\"footnote\" title=\"Clique para ir para a nota de rodapé 27\">27</a></sup>.</p>"
        },
        {
          "line_index": 8,
          "text": "Para fazer.",
          "raw_html": "<p class=\"wp-block-paragraph\">Para fazer<a name=\"rf28-20399\"></a><sup><a href=\"#fn28-20399\" rel=\"footnote\" title=\"Clique para ir para a nota de rodapé 28\">28</a></sup>.</p>"
        },
        {
          "line_index": 9,
          "text": "Para ele.",
          "raw_html": "<p class=\"wp-block-paragraph\">Para ele.</p>"
        },
        {
          "line_index": 10,
          "text": "Conforme que faz ele.",
          "raw_html": "<p class=\"wp-block-paragraph\">Conforme que faz ele<a name=\"rf29-20399\"></a><sup><a href=\"#fn29-20399\" rel=\"footnote\" title=\"Clique para ir para a nota de rodapé 29\">29</a></sup>.</p>"
        },
        {
          "line_index": 11,
          "text": "Para nós.",
          "raw_html": "<p class=\"wp-block-paragraph\">Para nós.</p>"
        }
      ]
    },
    {
      "number": 11,
      "text": "E descem três de milhares. Homem. Desde Yehudah. À fenda do rochedo de ‘Etam. E dizem eles para Shimshon. Acaso não conheces tu. Que governadores. Filhos de pelishtim. E qual essa. Fazes tu. Para nós? E diz ele para eles. Conforme que fazem eles. Para mim. Assim faço eu. Para eles.",
      "lines": [
        {
          "line_index": 0,
          "text": "E descem três de milhares.",
          "raw_html": "<p class=\"wp-block-paragraph\"> E descem três de<a name=\"rf30-20399\"></a><sup><a href=\"#fn30-20399\" rel=\"footnote\" title=\"Clique para ir para a nota de rodapé 30\">30</a></sup> milhares<a name=\"rf31-20399\"></a><sup><a href=\"#fn31-20399\" rel=\"footnote\" title=\"Clique para ir para a nota de rodapé 31\">31</a></sup><a name=\"rf32-20399\"></a><sup><a href=\"#fn32-20399\" rel=\"footnote\" title=\"Clique para ir para a nota de rodapé 32\">32</a></sup>.</p>"
        },
        {
          "line_index": 1,
          "text": "Homem.",
          "raw_html": "<p class=\"wp-block-paragraph\">Homem<a name=\"rf33-20399\"></a><sup><a href=\"#fn33-20399\" rel=\"footnote\" title=\"Clique para ir para a nota de rodapé 33\">33</a></sup>.</p>"
        },
        {
          "line_index": 2,
          "text": "Desde Yehudah.",
          "raw_html": "<p class=\"wp-block-paragraph\">Desde Yehudah.</p>"
        },
        {
          "line_index": 3,
          "text": "À fenda do rochedo de ‘Etam.",
          "raw_html": "<p class=\"wp-block-paragraph\">À fenda do rochedo de ‘Etam.</p>"
        },
        {
          "line_index": 4,
          "text": "E dizem eles para Shimshon.",
          "raw_html": "<p class=\"wp-block-paragraph\">E dizem eles para Shimshon.</p>"
        },
        {
          "line_index": 5,
          "text": "Acaso não conheces tu.",
          "raw_html": "<p class=\"wp-block-paragraph\">Acaso não conheces tu.</p>"
        },
        {
          "line_index": 6,
          "text": "Que governadores.",
          "raw_html": "<p class=\"wp-block-paragraph\">Que governadores<a name=\"rf34-20399\"></a><sup><a href=\"#fn34-20399\" rel=\"footnote\" title=\"Clique para ir para a nota de rodapé 34\">34</a></sup><a name=\"rf35-20399\"></a><sup><a href=\"#fn35-20399\" rel=\"footnote\" title=\"Clique para ir para a nota de rodapé 35\">35</a></sup>.</p>"
        },
        {
          "line_index": 7,
          "text": "Filhos de pelishtim.",
          "raw_html": "<p class=\"wp-block-paragraph\">Filhos de pelishtim.</p>"
        },
        {
          "line_index": 8,
          "text": "E qual essa.",
          "raw_html": "<p class=\"wp-block-paragraph\">E qual<a name=\"rf36-20399\"></a><sup><a href=\"#fn36-20399\" rel=\"footnote\" title=\"Clique para ir para a nota de rodapé 36\">36</a></sup> essa.</p>"
        },
        {
          "line_index": 9,
          "text": "Fazes tu.",
          "raw_html": "<p class=\"wp-block-paragraph\">Fazes tu<a name=\"rf37-20399\"></a><sup><a href=\"#fn37-20399\" rel=\"footnote\" title=\"Clique para ir para a nota de rodapé 37\">37</a></sup>.</p>"
        },
        {
          "line_index": 10,
          "text": "Para nós?",
          "raw_html": "<p class=\"wp-block-paragraph\">Para nós?</p>"
        },
        {
          "line_index": 11,
          "text": "E diz ele para eles.",
          "raw_html": "<p class=\"wp-block-paragraph\">E diz ele para eles.</p>"
        },
        {
          "line_index": 12,
          "text": "Conforme que fazem eles.",
          "raw_html": "<p class=\"wp-block-paragraph\">Conforme que fazem eles<a name=\"rf38-20399\"></a><sup><a href=\"#fn38-20399\" rel=\"footnote\" title=\"Clique para ir para a nota de rodapé 38\">38</a></sup>.</p>"
        },
        {
          "line_index": 13,
          "text": "Para mim.",
          "raw_html": "<p class=\"wp-block-paragraph\">Para mim.</p>"
        },
        {
          "line_index": 14,
          "text": "Assim faço eu.",
          "raw_html": "<p class=\"wp-block-paragraph\">Assim faço eu<a name=\"rf39-20399\"></a><sup><a href=\"#fn39-20399\" rel=\"footnote\" title=\"Clique para ir para a nota de rodapé 39\">39</a></sup>.</p>"
        },
        {
          "line_index": 15,
          "text": "Para eles.",
          "raw_html": "<p class=\"wp-block-paragraph\">Para eles.</p>"
        }
      ]
    },
    {
      "number": 12,
      "text": "E dizem eles para ele. Para o prender de ti. Descemos nós. Para o dar de ti. Em mão de pelishtim. E diz para eles Shimshon. Jurados estais vós para mim. Para que não encontrais em mim vós.",
      "lines": [
        {
          "line_index": 0,
          "text": "E dizem eles para ele.",
          "raw_html": "<p class=\"wp-block-paragraph\">E dizem eles para ele.</p>"
        },
        {
          "line_index": 1,
          "text": "Para o prender de ti.",
          "raw_html": "<p class=\"wp-block-paragraph\">Para o prender de ti.</p>"
        },
        {
          "line_index": 2,
          "text": "Descemos nós.",
          "raw_html": "<p class=\"wp-block-paragraph\">Descemos nós.</p>"
        },
        {
          "line_index": 3,
          "text": "Para o dar de ti.",
          "raw_html": "<p class=\"wp-block-paragraph\">Para o dar de ti.</p>"
        },
        {
          "line_index": 4,
          "text": "Em mão de pelishtim.",
          "raw_html": "<p class=\"wp-block-paragraph\">Em mão de<a name=\"rf40-20399\"></a><sup><a href=\"#fn40-20399\" rel=\"footnote\" title=\"Clique para ir para a nota de rodapé 40\">40</a></sup> pelishtim.</p>"
        },
        {
          "line_index": 5,
          "text": "E diz para eles Shimshon.",
          "raw_html": "<p class=\"wp-block-paragraph\">E diz para eles Shimshon.</p>"
        },
        {
          "line_index": 6,
          "text": "Jurados estais vós para mim.",
          "raw_html": "<p class=\"wp-block-paragraph\">Jurados estais vós para mim.</p>"
        },
        {
          "line_index": 7,
          "text": "Para que não encontrais em mim vós.",
          "raw_html": "<p class=\"wp-block-paragraph\">Para que não encontrais em mim vós.</p>"
        }
      ]
    },
    {
      "number": 13,
      "text": "E dizem eles. Para ele. Para dizer. Não. Que prender. Prendemos nós tu. E damos nós tu. Na mão deles. E fazer morrer. Não fazemos nós morrer tu. E prendem eles ele. Em dois cordoamentos novos. E fazem eles subir ele. Desde o rochedo.",
      "lines": [
        {
          "line_index": 0,
          "text": "E dizem eles.",
          "raw_html": "<p class=\"wp-block-paragraph\"> E dizem eles.</p>"
        },
        {
          "line_index": 1,
          "text": "Para ele.",
          "raw_html": "<p class=\"wp-block-paragraph\">Para ele.</p>"
        },
        {
          "line_index": 2,
          "text": "Para dizer.",
          "raw_html": "<p class=\"wp-block-paragraph\">Para dizer.</p>"
        },
        {
          "line_index": 3,
          "text": "Não.",
          "raw_html": "<p class=\"wp-block-paragraph\">Não.</p>"
        },
        {
          "line_index": 4,
          "text": "Que prender.",
          "raw_html": "<p class=\"wp-block-paragraph\">Que prender.</p>"
        },
        {
          "line_index": 5,
          "text": "Prendemos nós tu.",
          "raw_html": "<p class=\"wp-block-paragraph\">Prendemos nós tu.</p>"
        },
        {
          "line_index": 6,
          "text": "E damos nós tu.",
          "raw_html": "<p class=\"wp-block-paragraph\">E damos nós tu.</p>"
        },
        {
          "line_index": 7,
          "text": "Na mão deles.",
          "raw_html": "<p class=\"wp-block-paragraph\">Na mão deles.</p>"
        },
        {
          "line_index": 8,
          "text": "E fazer morrer.",
          "raw_html": "<p class=\"wp-block-paragraph\">E fazer morrer<a name=\"rf41-20399\"></a><sup><a href=\"#fn41-20399\" rel=\"footnote\" title=\"Clique para ir para a nota de rodapé 41\">41</a></sup>.</p>"
        },
        {
          "line_index": 9,
          "text": "Não fazemos nós morrer tu.",
          "raw_html": "<p class=\"wp-block-paragraph\">Não fazemos nós morrer<a name=\"rf42-20399\"></a><sup><a href=\"#fn42-20399\" rel=\"footnote\" title=\"Clique para ir para a nota de rodapé 42\">42</a></sup> tu.</p>"
        },
        {
          "line_index": 10,
          "text": "E prendem eles ele.",
          "raw_html": "<p class=\"wp-block-paragraph\">E prendem eles ele.</p>"
        },
        {
          "line_index": 11,
          "text": "Em dois cordoamentos novos.",
          "raw_html": "<p class=\"wp-block-paragraph\">Em dois cordoamentos novos.</p>"
        },
        {
          "line_index": 12,
          "text": "E fazem eles subir ele.",
          "raw_html": "<p class=\"wp-block-paragraph\">E fazem eles subir<a name=\"rf43-20399\"></a><sup><a href=\"#fn43-20399\" rel=\"footnote\" title=\"Clique para ir para a nota de rodapé 43\">43</a></sup> ele.</p>"
        },
        {
          "line_index": 13,
          "text": "Desde o rochedo.",
          "raw_html": "<p class=\"wp-block-paragraph\">Desde o rochedo.</p>"
        }
      ]
    },
    {
      "number": 14,
      "text": "Ele. Idor. Até Lehi. E pelishtim. Fazedores de aclamar. Para o gritar dele. E prospera. Sobre ele. A ventania de Yahweh. E estão elas. As cordoamentações. Que sobre os braços dele. Conforme cambraiados. Que queimam eles. Na flama. E dissolvidos. Os prendimentos dele. Desde sobre as mãos dele.",
      "lines": [
        {
          "line_index": 0,
          "text": "Ele.",
          "raw_html": "<p class=\"wp-block-paragraph\"> Ele.</p>"
        },
        {
          "line_index": 1,
          "text": "Idor.",
          "raw_html": "<p class=\"wp-block-paragraph\">Idor<a name=\"rf44-20399\"></a><sup><a href=\"#fn44-20399\" rel=\"footnote\" title=\"Clique para ir para a nota de rodapé 44\">44</a></sup>.</p>"
        },
        {
          "line_index": 2,
          "text": "Até Lehi.",
          "raw_html": "<p class=\"wp-block-paragraph\">Até Lehi.</p>"
        },
        {
          "line_index": 3,
          "text": "E pelishtim.",
          "raw_html": "<p class=\"wp-block-paragraph\">E pelishtim.</p>"
        },
        {
          "line_index": 4,
          "text": "Fazedores de aclamar.",
          "raw_html": "<p class=\"wp-block-paragraph\">Fazedores de aclamar.</p>"
        },
        {
          "line_index": 5,
          "text": "Para o gritar dele.",
          "raw_html": "<p class=\"wp-block-paragraph\">Para o gritar dele.</p>"
        },
        {
          "line_index": 6,
          "text": "E prospera.",
          "raw_html": "<p class=\"wp-block-paragraph\">E prospera.</p>"
        },
        {
          "line_index": 7,
          "text": "Sobre ele.",
          "raw_html": "<p class=\"wp-block-paragraph\">Sobre ele.</p>"
        },
        {
          "line_index": 8,
          "text": "A ventania de Yahweh.",
          "raw_html": "<p class=\"wp-block-paragraph\">A ventania de Yahweh.</p>"
        },
        {
          "line_index": 9,
          "text": "E estão elas.",
          "raw_html": "<p class=\"wp-block-paragraph\">E estão elas<a name=\"rf45-20399\"></a><sup><a href=\"#fn45-20399\" rel=\"footnote\" title=\"Clique para ir para a nota de rodapé 45\">45</a></sup>.</p>"
        },
        {
          "line_index": 10,
          "text": "As cordoamentações.",
          "raw_html": "<p class=\"wp-block-paragraph\">As cordoamentações<a name=\"rf46-20399\"></a><sup><a href=\"#fn46-20399\" rel=\"footnote\" title=\"Clique para ir para a nota de rodapé 46\">46</a></sup>.</p>"
        },
        {
          "line_index": 11,
          "text": "Que sobre os braços dele.",
          "raw_html": "<p class=\"wp-block-paragraph\">Que sobre os braços dele.</p>"
        },
        {
          "line_index": 12,
          "text": "Conforme cambraiados.",
          "raw_html": "<p class=\"wp-block-paragraph\">Conforme cambraiados.</p>"
        },
        {
          "line_index": 13,
          "text": "Que queimam eles.",
          "raw_html": "<p class=\"wp-block-paragraph\">Que queimam eles.</p>"
        },
        {
          "line_index": 14,
          "text": "Na flama.",
          "raw_html": "<p class=\"wp-block-paragraph\">Na flama<a name=\"rf47-20399\"></a><sup><a href=\"#fn47-20399\" rel=\"footnote\" title=\"Clique para ir para a nota de rodapé 47\">47</a></sup>.</p>"
        },
        {
          "line_index": 15,
          "text": "E dissolvidos.",
          "raw_html": "<p class=\"wp-block-paragraph\">E dissolvidos.</p>"
        },
        {
          "line_index": 16,
          "text": "Os prendimentos dele.",
          "raw_html": "<p class=\"wp-block-paragraph\">Os prendimentos dele.</p>"
        },
        {
          "line_index": 17,
          "text": "Desde sobre as mãos dele.",
          "raw_html": "<p class=\"wp-block-paragraph\">Desde sobre as mãos dele<a name=\"rf48-20399\"></a><sup><a href=\"#fn48-20399\" rel=\"footnote\" title=\"Clique para ir para a nota de rodapé 48\">48</a></sup>.</p>"
        }
      ]
    },
    {
      "number": 15,
      "text": "E encontra ele. Mandíbula de jumento fresca. E envia ele a mão dele. E toma ele ela. E faz ele ferir. Nela. Milhar de homem.",
      "lines": [
        {
          "line_index": 0,
          "text": "E encontra ele.",
          "raw_html": "<p class=\"wp-block-paragraph\"> E encontra ele.</p>"
        },
        {
          "line_index": 1,
          "text": "Mandíbula de jumento fresca.",
          "raw_html": "<p class=\"wp-block-paragraph\">Mandíbula de jumento fresca.</p>"
        },
        {
          "line_index": 2,
          "text": "E envia ele a mão dele.",
          "raw_html": "<p class=\"wp-block-paragraph\">E envia ele<a name=\"rf49-20399\"></a><sup><a href=\"#fn49-20399\" rel=\"footnote\" title=\"Clique para ir para a nota de rodapé 49\">49</a></sup><a name=\"rf50-20399\"></a><sup><a href=\"#fn50-20399\" rel=\"footnote\" title=\"Clique para ir para a nota de rodapé 50\">50</a></sup> a mão dele<a name=\"rf51-20399\"></a><sup><a href=\"#fn51-20399\" rel=\"footnote\" title=\"Clique para ir para a nota de rodapé 51\">51</a></sup>.</p>"
        },
        {
          "line_index": 3,
          "text": "E toma ele ela.",
          "raw_html": "<p class=\"wp-block-paragraph\">E toma ele ela<a name=\"rf52-20399\"></a><sup><a href=\"#fn52-20399\" rel=\"footnote\" title=\"Clique para ir para a nota de rodapé 52\">52</a></sup>.</p>"
        },
        {
          "line_index": 4,
          "text": "E faz ele ferir.",
          "raw_html": "<p class=\"wp-block-paragraph\">E faz ele ferir<a name=\"rf53-20399\"></a><sup><a href=\"#fn53-20399\" rel=\"footnote\" title=\"Clique para ir para a nota de rodapé 53\">53</a></sup>.</p>"
        },
        {
          "line_index": 5,
          "text": "Nela.",
          "raw_html": "<p class=\"wp-block-paragraph\">Nela.</p>"
        },
        {
          "line_index": 6,
          "text": "Milhar de homem.",
          "raw_html": "<p class=\"wp-block-paragraph\">Milhar de homem.</p>"
        }
      ]
    },
    {
      "number": 16,
      "text": "E diz Shimshon. Na queixada do jumento. Jumento. Dois-jumentos. Na queixada do jumento. Faço eu ferir. Mil de homem.",
      "lines": [
        {
          "line_index": 0,
          "text": "E diz Shimshon.",
          "raw_html": "<p class=\"wp-block-paragraph\">E diz Shimshon.</p>"
        },
        {
          "line_index": 1,
          "text": "Na queixada do jumento.",
          "raw_html": "<p class=\"wp-block-paragraph\">Na queixada do jumento.</p>"
        },
        {
          "line_index": 2,
          "text": "Jumento.",
          "raw_html": "<p class=\"wp-block-paragraph\">Jumento.</p>"
        },
        {
          "line_index": 3,
          "text": "Dois-jumentos.",
          "raw_html": "<p class=\"wp-block-paragraph\">Dois-jumentos.</p>"
        },
        {
          "line_index": 4,
          "text": "Na queixada do jumento.",
          "raw_html": "<p class=\"wp-block-paragraph\">Na queixada do jumento.</p>"
        },
        {
          "line_index": 5,
          "text": "Faço eu ferir.",
          "raw_html": "<p class=\"wp-block-paragraph\">Faço eu ferir<a name=\"rf54-20399\"></a><sup><a href=\"#fn54-20399\" rel=\"footnote\" title=\"Clique para ir para a nota de rodapé 54\">54</a></sup>.</p>"
        },
        {
          "line_index": 6,
          "text": "Mil de homem.",
          "raw_html": "<p class=\"wp-block-paragraph\">Mil de homem.</p>"
        }
      ]
    },
    {
      "number": 17,
      "text": "E está. Conforme o acabar dele. Para falar. E lança ele a queixada. Desde a mão dele. E grita ele. Para o lugar aquele. Ramat Lehi.",
      "lines": [
        {
          "line_index": 0,
          "text": "E está.",
          "raw_html": "<p class=\"wp-block-paragraph\"> E está<a name=\"rf55-20399\"></a><sup><a href=\"#fn55-20399\" rel=\"footnote\" title=\"Clique para ir para a nota de rodapé 55\">55</a></sup><a name=\"rf56-20399\"></a><sup><a href=\"#fn56-20399\" rel=\"footnote\" title=\"Clique para ir para a nota de rodapé 56\">56</a></sup>.</p>"
        },
        {
          "line_index": 1,
          "text": "Conforme o acabar dele.",
          "raw_html": "<p class=\"wp-block-paragraph\">Conforme o acabar dele.</p>"
        },
        {
          "line_index": 2,
          "text": "Para falar.",
          "raw_html": "<p class=\"wp-block-paragraph\">Para falar.</p>"
        },
        {
          "line_index": 3,
          "text": "E lança ele a queixada.",
          "raw_html": "<p class=\"wp-block-paragraph\">E lança ele a queixada.</p>"
        },
        {
          "line_index": 4,
          "text": "Desde a mão dele.",
          "raw_html": "<p class=\"wp-block-paragraph\">Desde a mão dele<a name=\"rf57-20399\"></a><sup><a href=\"#fn57-20399\" rel=\"footnote\" title=\"Clique para ir para a nota de rodapé 57\">57</a></sup>.</p>"
        },
        {
          "line_index": 5,
          "text": "E grita ele.",
          "raw_html": "<p class=\"wp-block-paragraph\">E grita ele.</p>"
        },
        {
          "line_index": 6,
          "text": "Para o lugar aquele.",
          "raw_html": "<p class=\"wp-block-paragraph\">Para o lugar aquele.</p>"
        },
        {
          "line_index": 7,
          "text": "Ramat Lehi.",
          "raw_html": "<p class=\"wp-block-paragraph\">Ramat Lehi.</p>"
        }
      ]
    },
    {
      "number": 18,
      "text": "E sedenta ele muito. E grita ele a Yahweh. E diz ele. Tu. Dás tu. Na mão do servo de ti. A salvação grande essa. E agora. Morro eu. Na sede. E caio eu. Na mão dos incircuncisos?",
      "lines": [
        {
          "line_index": 0,
          "text": "E sedenta ele muito.",
          "raw_html": "<p class=\"wp-block-paragraph\"> E sedenta ele muito.</p>"
        },
        {
          "line_index": 1,
          "text": "E grita ele a Yahweh.",
          "raw_html": "<p class=\"wp-block-paragraph\">E grita ele a Yahweh.</p>"
        },
        {
          "line_index": 2,
          "text": "E diz ele.",
          "raw_html": "<p class=\"wp-block-paragraph\">E diz ele.</p>"
        },
        {
          "line_index": 3,
          "text": "Tu.",
          "raw_html": "<p class=\"wp-block-paragraph\">Tu.</p>"
        },
        {
          "line_index": 4,
          "text": "Dás tu.",
          "raw_html": "<p class=\"wp-block-paragraph\">Dás tu.</p>"
        },
        {
          "line_index": 5,
          "text": "Na mão do servo de ti.",
          "raw_html": "<p class=\"wp-block-paragraph\">Na mão do<a name=\"rf58-20399\"></a><sup><a href=\"#fn58-20399\" rel=\"footnote\" title=\"Clique para ir para a nota de rodapé 58\">58</a></sup> servo de<a name=\"rf59-20399\"></a><sup><a href=\"#fn59-20399\" rel=\"footnote\" title=\"Clique para ir para a nota de rodapé 59\">59</a></sup> ti.</p>"
        },
        {
          "line_index": 6,
          "text": "A salvação grande essa.",
          "raw_html": "<p class=\"wp-block-paragraph\">A salvação grande essa.</p>"
        },
        {
          "line_index": 7,
          "text": "E agora.",
          "raw_html": "<p class=\"wp-block-paragraph\">E agora<a name=\"rf60-20399\"></a><sup><a href=\"#fn60-20399\" rel=\"footnote\" title=\"Clique para ir para a nota de rodapé 60\">60</a></sup><a name=\"rf61-20399\"></a><sup><a href=\"#fn61-20399\" rel=\"footnote\" title=\"Clique para ir para a nota de rodapé 61\">61</a></sup>.</p>"
        },
        {
          "line_index": 8,
          "text": "Morro eu.",
          "raw_html": "<p class=\"wp-block-paragraph\">Morro eu<a name=\"rf62-20399\"></a><sup><a href=\"#fn62-20399\" rel=\"footnote\" title=\"Clique para ir para a nota de rodapé 62\">62</a></sup>.</p>"
        },
        {
          "line_index": 9,
          "text": "Na sede.",
          "raw_html": "<p class=\"wp-block-paragraph\">Na sede.</p>"
        },
        {
          "line_index": 10,
          "text": "E caio eu.",
          "raw_html": "<p class=\"wp-block-paragraph\">E caio eu.</p>"
        },
        {
          "line_index": 11,
          "text": "Na mão dos incircuncisos?",
          "raw_html": "<p class=\"wp-block-paragraph\">Na mão dos<a name=\"rf63-20399\"></a><sup><a href=\"#fn63-20399\" rel=\"footnote\" title=\"Clique para ir para a nota de rodapé 63\">63</a></sup> incircuncisos?</p>"
        }
      ]
    },
    {
      "number": 19,
      "text": "E rompe ‘Elohim. O almofariz. Que na Lehi. E saem. Desde ele. Aquosos. E bebe ele. E volta a ventania dele. E vive ele. Sobre assim. Grita ele. O nome dela. ‘En Haqqore’. Que na Lehi. Até o dia esse.",
      "lines": [
        {
          "line_index": 0,
          "text": "E rompe ‘Elohim.",
          "raw_html": "<p class=\"wp-block-paragraph\"> E rompe ‘Elohim.</p>"
        },
        {
          "line_index": 1,
          "text": "O almofariz.",
          "raw_html": "<p class=\"wp-block-paragraph\">O almofariz.</p>"
        },
        {
          "line_index": 2,
          "text": "Que na Lehi.",
          "raw_html": "<p class=\"wp-block-paragraph\">Que na Lehi.</p>"
        },
        {
          "line_index": 3,
          "text": "E saem.",
          "raw_html": "<p class=\"wp-block-paragraph\">E saem.</p>"
        },
        {
          "line_index": 4,
          "text": "Desde ele.",
          "raw_html": "<p class=\"wp-block-paragraph\">Desde ele.</p>"
        },
        {
          "line_index": 5,
          "text": "Aquosos.",
          "raw_html": "<p class=\"wp-block-paragraph\">Aquosos.</p>"
        },
        {
          "line_index": 6,
          "text": "E bebe ele.",
          "raw_html": "<p class=\"wp-block-paragraph\">E bebe ele.</p>"
        },
        {
          "line_index": 7,
          "text": "E volta a ventania dele.",
          "raw_html": "<p class=\"wp-block-paragraph\">E volta<a name=\"rf64-20399\"></a><sup><a href=\"#fn64-20399\" rel=\"footnote\" title=\"Clique para ir para a nota de rodapé 64\">64</a></sup> a ventania dele.</p>"
        },
        {
          "line_index": 8,
          "text": "E vive ele.",
          "raw_html": "<p class=\"wp-block-paragraph\">E vive ele<a name=\"rf65-20399\"></a><sup><a href=\"#fn65-20399\" rel=\"footnote\" title=\"Clique para ir para a nota de rodapé 65\">65</a></sup>.</p>"
        },
        {
          "line_index": 9,
          "text": "Sobre assim.",
          "raw_html": "<p class=\"wp-block-paragraph\">Sobre assim.</p>"
        },
        {
          "line_index": 10,
          "text": "Grita ele.",
          "raw_html": "<p class=\"wp-block-paragraph\">Grita ele.</p>"
        },
        {
          "line_index": 11,
          "text": "O nome dela.",
          "raw_html": "<p class=\"wp-block-paragraph\">O nome dela<a name=\"rf66-20399\"></a><sup><a href=\"#fn66-20399\" rel=\"footnote\" title=\"Clique para ir para a nota de rodapé 66\">66</a></sup><a name=\"rf67-20399\"></a><sup><a href=\"#fn67-20399\" rel=\"footnote\" title=\"Clique para ir para a nota de rodapé 67\">67</a></sup>.</p>"
        },
        {
          "line_index": 12,
          "text": "‘En Haqqore’.",
          "raw_html": "<p class=\"wp-block-paragraph\">‘En Haqqore’.</p>"
        },
        {
          "line_index": 13,
          "text": "Que na Lehi.",
          "raw_html": "<p class=\"wp-block-paragraph\">Que na Lehi.</p>"
        },
        {
          "line_index": 14,
          "text": "Até o dia esse.",
          "raw_html": "<p class=\"wp-block-paragraph\">Até o dia<a name=\"rf68-20399\"></a><sup><a href=\"#fn68-20399\" rel=\"footnote\" title=\"Clique para ir para a nota de rodapé 68\">68</a></sup> esse<a name=\"rf69-20399\"></a><sup><a href=\"#fn69-20399\" rel=\"footnote\" title=\"Clique para ir para a nota de rodapé 69\">69</a></sup><a name=\"rf70-20399\"></a><sup><a href=\"#fn70-20399\" rel=\"footnote\" title=\"Clique para ir para a nota de rodapé 70\">70</a></sup>.</p>"
        }
      ]
    },
    {
      "number": 20,
      "text": "E julga ele Yisra’el. Em dias de pelishyim. Vinte mudança.",
      "lines": [
        {
          "line_index": 0,
          "text": "E julga ele Yisra’el.",
          "raw_html": "<p class=\"wp-block-paragraph\"> E julga ele Yisra’el.</p>"
        },
        {
          "line_index": 1,
          "text": "Em dias de pelishyim.",
          "raw_html": "<p class=\"wp-block-paragraph\">Em dias de pelishyim.</p>"
        },
        {
          "line_index": 2,
          "text": "Vinte mudança.",
          "raw_html": "<p class=\"wp-block-paragraph\">Vinte mudança.</p>"
        }
      ]
    }
  ],
  "footnotes": [
    {
      "ref_id": "fn1-20399",
      "number": 1,
      "text": "“Está” (hyh).",
      "raw_html": "<span>“<a data-id=\"https://nossabiblialivre.com/referencias/#AAAAB\" data-type=\"link\" href=\"https://nossabiblialivre.com/referencias/#AAAAB\" rel=\"noopener\" target=\"_blank\">Está</a>” (<em>hyh</em>). </span>"
    },
    {
      "ref_id": "fn2-20399",
      "number": 2,
      "text": "“E está” (wayehi).",
      "raw_html": "<span>“<a data-id=\"24610\" data-type=\"page\" href=\"https://nossabiblialivre.com/referencias/#AAAAA\" rel=\"noreferrer noopener\" target=\"_blank\">E está</a>” (<em>wayehi</em>). </span>"
    },
    {
      "ref_id": "fn3-20399",
      "number": 3,
      "text": "“Visita” (pqd). Cf. Gênesis 21,1; Josué 8,10; 10,18; Juízes 15,1; 20,15.17; 21,3.9; Rute 1,6; 1 Samuel 2,21; 11,8; 13,15; 14,17; 15,2.4; 17,18; 20,6.18.25.27; 25,7.15.21.",
      "raw_html": "<span>“Visita” (<em>pqd</em>). Cf. Gênesis 21,1; Josué 8,10; 10,18; Juízes 15,1; 20,15.17; 21,3.9; Rute 1,6; 1 Samuel 2,21; 11,8; 13,15; 14,17; 15,2.4; 17,18; 20,6.18.25.27; 25,7.15.21. </span>"
    },
    {
      "ref_id": "fn4-20399",
      "number": 4,
      "text": "“Cabras” (‘izzim [‘ez]). Cf. Gênesis 15,9; Juízes 6,19; 13,15.19; 15,1; 1 Samuel 16,20; 19,13.16; 25,2.",
      "raw_html": "<span>“Cabras” (<em>‘izzim</em> [<em>‘ez</em>]). Cf. Gênesis 15,9; Juízes 6,19; 13,15.19; 15,1; 1 Samuel 16,20; 19,13.16; 25,2. </span>"
    },
    {
      "ref_id": "fn5-20399",
      "number": 5,
      "text": "“Vou eu” (bw’). Cf. Gênesis 2,19; Josué 10,9.13.19.20.27; 11,5.7.21; 13,1; 14,11; 15,18; 18,3.4.6.9; 20,6; 21,45; 22,10.15; 23,1.2.7.12.14.15; 24,6.7.8.11; Juízes 1,7.14; 2,1; 3,20.22.24.27; 4,20.21.22; 5,19.23.28; 6,4.5.11.18.19; 7,13.17.19.25; 8,4.15; 9,5.15.24.26.27.31.37.46.52.57; 11,7.12.16.18.33.34; 12,9; 13,6.8.9.11.12.17; 14,5.18; 15,1.14; 16,1.2; 17,8.9; 18,2.3.7.8.9.10.13.15.17.18.20.27; 19,3.10.14.15.16.17.21.22.23.26.29; 20,4.10.26.34; 21,2.8.12; 1 Samuel 1,19.22.24.25; 2,13.14.15.27.31.34.36; 3,10; 4,3.5.6.7.12.13.14.16; 5,1.2.5.10; 6,14; 7,1.13; 8,4; 9,5.6.7.12.13.14.15.16.22; 10,3.5.7.8.9.10.13.14.22.27; 11,4,5,9,11; 12,8.12; 13,8.10.11; 14,20.25.26; 15,5.12.13.15.20; 16,2.4.5.6.11.12.17.21; 17,12,18.20.34.43.45.52.54.57; 18,6.13.16.27; 9,7.16.18.22.23; 20,1.8.9.19.21.27.29.37.38.40.41; 21,1.2.11.15.16; 22,5.9.11; 23,7.10.27.27; 24,4; 25,5.8.9.12.19.26.27.33.34.35.36.40; 26,1.3.4.5.7.10.15.",
      "raw_html": "<span>“Vou eu” (<em>bw’</em>). Cf. Gênesis 2,19; Josué 10,9.13.19.20.27; 11,5.7.21; 13,1; 14,11; 15,18; 18,3.4.6.9; 20,6; 21,45; 22,10.15; 23,1.2.7.12.14.15; 24,6.7.8.11; Juízes 1,7.14; 2,1; 3,20.22.24.27; 4,20.21.22; 5,19.23.28; 6,4.5.11.18.19; 7,13.17.19.25; 8,4.15; 9,5.15.24.26.27.31.37.46.52.57; 11,7.12.16.18.33.34; 12,9; 13,6.8.9.11.12.17; 14,5.18; 15,1.14; 16,1.2; 17,8.9; 18,2.3.7.8.9.10.13.15.17.18.20.27; 19,3.10.14.15.16.17.21.22.23.26.29; 20,4.10.26.34; 21,2.8.12; 1 Samuel 1,19.22.24.25; 2,13.14.15.27.31.34.36; 3,10; 4,3.5.6.7.12.13.14.16; 5,1.2.5.10; 6,14; 7,1.13; 8,4; 9,5.6.7.12.13.14.15.16.22; 10,3.5.7.8.9.10.13.14.22.27; 11,4,5,9,11; 12,8.12; 13,8.10.11; 14,20.25.26; 15,5.12.13.15.20; 16,2.4.5.6.11.12.17.21; 17,12,18.20.34.43.45.52.54.57; 18,6.13.16.27; 9,7.16.18.22.23; 20,1.8.9.19.21.27.29.37.38.40.41; 21,1.2.11.15.16; 22,5.9.11; 23,7.10.27.27; 24,4; 25,5.8.9.12.19.26.27.33.34.35.36.40; 26,1.3.4.5.7.10.15. </span>"
    },
    {
      "ref_id": "fn6-20399",
      "number": 6,
      "text": "“Ir” (bw’). Forma infinitiva da raiz. Cf. acima.",
      "raw_html": "<span>“Ir” (<em>bw’</em>). Forma infinitiva da raiz. Cf. acima. </span>"
    },
    {
      "ref_id": "fn7-20399",
      "number": 7,
      "text": "“A irmã de” (‘ahot).",
      "raw_html": "<span>“<a data-id=\"https://nossabiblialivre.com/referencias/#AAAKH\" data-type=\"link\" href=\"https://nossabiblialivre.com/referencias/#AAAKH\" rel=\"noreferrer noopener\" target=\"_blank\">A irmã de</a>” (<em>‘ahot</em>). </span>"
    },
    {
      "ref_id": "fn8-20399",
      "number": 8,
      "text": "“Está ela” (hyh).",
      "raw_html": "<span>“<a data-id=\"https://nossabiblialivre.com/referencias/#AAAAB\" data-type=\"link\" href=\"https://nossabiblialivre.com/referencias/#AAAAB\" rel=\"noopener\" target=\"_blank\">Está ela</a>” (<em>hyh</em>). </span>"
    },
    {
      "ref_id": "fn9-20399",
      "number": 9,
      "text": "“Debaixo de” (tahat).",
      "raw_html": "<span>“<a data-id=\"https://nossabiblialivre.com/referencias/#AAAHU\" data-type=\"link\" href=\"https://nossabiblialivre.com/referencias/#AAAHU\" rel=\"noreferrer noopener\" target=\"_blank\">Debaixo de</a>” (<em>tahat</em>). </span>"
    },
    {
      "ref_id": "fn10-20399",
      "number": 10,
      "text": "“Livrado estou eu” (nqh). Forma passiva da raiz. Cf. Gênesis 24,8.41; Êxodo 20,7; 21,19; 34,7; Números 5,19.28.31; Números 14,18; Deuteronômio 5,11; Juízes 5,3; 1 Samuel 26,9.",
      "raw_html": "<span>“Livrado estou eu” (<em>nqh</em>). Forma passiva da raiz. Cf. Gênesis 24,8.41; Êxodo 20,7; 21,19; 34,7; Números 5,19.28.31; Números 14,18; Deuteronômio 5,11; Juízes 5,3; 1 Samuel 26,9. </span>"
    },
    {
      "ref_id": "fn11-20399",
      "number": 11,
      "text": "“Maldade” (ra’ah). Cf. Gênesis 6,5; Juízes 2,15; 9,56.57; 11,27.37.38; 15,3; 20,3.12.13.34.41; 1 Samuel 6,9; 10,19; 12,17.19.20; 20,7.9.13; 23,9; 24,10.12.18; 25,17.21.26.38.39; 26,18.",
      "raw_html": "<span>“Maldade” (<em>ra’ah</em>). Cf. Gênesis 6,5; Juízes 2,15; 9,56.57; 11,27.37.38; 15,3; 20,3.12.13.34.41; 1 Samuel 6,9; 10,19; 12,17.19.20; 20,7.9.13; 23,9; 24,10.12.18; 25,17.21.26.38.39; 26,18. </span>"
    },
    {
      "ref_id": "fn12-20399",
      "number": 12,
      "text": "“Raposas” (shu’alim). Costuma-se identificar tais animais com a subespécie vulpes vulpes niloticus. Mas há quem afirme não se tratar de “raposas”, mas de “chacais”.",
      "raw_html": "<span>“Raposas” (<em>shu’alim</em>). Costuma-se identificar tais animais com a subespécie <em><a href=\"https://species.wikimedia.org/wiki/Vulpes_vulpes_niloticus\">vulpes vulpes niloticus</a></em>. Mas há quem afirme não se tratar de “raposas”, mas de “chacais”. </span>"
    },
    {
      "ref_id": "fn13-20399",
      "number": 13,
      "text": "“Despede ele” (shlh). Cf. Gênesis 3,22; Josué 10,3.6; 11,1; 14,7.11; 18,4; 22,6.7.13; 24,5.9.12.28; Juízes 1,8.25; 2,6; 3,15.18.21; 4,6; 5,15.26; 6,8.14.21.35; 7,8.24; 9,23.31; 11,12.14.17.19.28.38; 12,9; 13,8; 15,5.15; 16,18; 18,2; 19,25.29; 20,6.12.48; 21,10.13; 1 Samuel 4,4; 5,8.10.11; 6,2.3.6.8.21; 9,16.19.26; 10,25; 11,13.7; 12,8.11; 13,2; 14,27; 15,1.18.20; 16,1.11.12.19.20.22; 17,49; 18,5; 19,11.14.15.17.20.21; 20,5.12.13.20.21.22.29.31; 21,3; 22,11.17; 24,7.11.20; 25,5.14.25.32.39.40; 26,4.9.11.23; 30,26; 31,9.",
      "raw_html": "<span>“Despede ele” (<em>shlh</em>). Cf. Gênesis 3,22; Josué 10,3.6; 11,1; 14,7.11; 18,4; 22,6.7.13; 24,5.9.12.28; Juízes 1,8.25; 2,6; 3,15.18.21; 4,6; 5,15.26; 6,8.14.21.35; 7,8.24; 9,23.31; 11,12.14.17.19.28.38; 12,9; 13,8; 15,5.15; 16,18; 18,2; 19,25.29; 20,6.12.48; 21,10.13; 1 Samuel 4,4; 5,8.10.11; 6,2.3.6.8.21; 9,16.19.26; 10,25; 11,13.7; 12,8.11; 13,2; 14,27; 15,1.18.20; 16,1.11.12.19.20.22; 17,49; 18,5; 19,11.14.15.17.20.21; 20,5.12.13.20.21.22.29.31; 21,3; 22,11.17; 24,7.11.20; 25,5.14.25.32.39.40; 26,4.9.11.23; 30,26; 31,9. </span>"
    },
    {
      "ref_id": "fn14-20399",
      "number": 14,
      "text": "“Quem” (mi). Cf. Gênesis 3,11; Josué 9,8; 24,15; Juízes 1,1. 6,29; 7,3; 9,28.29; 10,18; 13,17; 15,6; 18,3; 20,18; 21,15; Juízes 21,8; Rute 2,5; 39.16; 1 Samuel 2,25; 4,8; 6,20; 9,20; 10,12; 11,12; 12,3; 14,17; 17,26.28.55.56.58; 18,18; 20,10; 22,14; 23,22; 24,15; 25,10; 26,6.9.14.15; 28,11; 30,13.24.",
      "raw_html": "<span>“Quem” (<em>mi</em>). Cf. Gênesis 3,11; Josué 9,8; 24,15; Juízes 1,1. 6,29; 7,3; 9,28.29; 10,18; 13,17; 15,6; 18,3; 20,18; 21,15; Juízes 21,8; Rute 2,5; 39.16; 1 Samuel 2,25; 4,8; 6,20; 9,20; 10,12; 11,12; 12,3; 14,17; 17,26.28.55.56.58; 18,18; 20,10; 22,14; 23,22; 24,15; 25,10; 26,6.9.14.15; 28,11; 30,13.24. </span>"
    },
    {
      "ref_id": "fn15-20399",
      "number": 15,
      "text": "“Faz” (‘sh). Cf. Gênesis 1,7; Josué 22,5.23.24.26.28; 23,3.6.8; 24,5.7.17.31; Juízes 1,7.24; 2,2.7.10.11; 3,7.12.16; 5,1; 6,1.2.17.19.20.27.29.40; 7,17; 8,1.2.3.27.35; 9,16.19.27.33.48.56; 10,6.15; 11,10.27.36.37.39; 13,1.8.15.16.19; 14,6.10; 15,3.6.7.10.11; 16,11; 17,3.4.5.6.8; 18,3.4.14.18.24.27.31; 19,23.24; 20,6.9.10; 21,7.11.15.16.23.25; Rute 1,8.17; 2,11.19; 3,4.5.6.11; 4,11; 1 Samuel 1,7.23; 2,14.19.22.23.35; 3,11.17.18; 5,87; 6,2,5,7,9,10; 8,8.12.16; 10,2.7.8; 11,7.10.13; 12,6.7.16.17.20.22; 13,11.19; 14,6.7.36.40.44.44.45.48; 15,2.6.19; 16,3.4; 17,25.26.27.29; 19,5.18; 20,1.2.4.8.13.14.32; 22,3; 24,5.7.19.20; 25,17.18.22.28.30; 26,16.18.25.",
      "raw_html": "<span>“Faz” (<em>‘sh</em>). Cf. Gênesis 1,7; Josué 22,5.23.24.26.28; 23,3.6.8; 24,5.7.17.31; Juízes 1,7.24; 2,2.7.10.11; 3,7.12.16; 5,1; 6,1.2.17.19.20.27.29.40; 7,17; <mark class=\"has-inline-color has-black-color\" style=\"background-color:rgba(0, 0, 0, 0)\">8,1.2.3.27.35</mark>; 9,16.19.27.33.48.56; 10,6.15; 11,10.27.36.37.39; 13,1.8.15.16.19; 14,6.10; 15,3.6.7.10.11; 16,11; 17,3.4.5.6.8; 18,3.4.14.18.24.27.31; 19,23.24; 20,6.9.10; 21,7.11.15.16.23.25; Rute 1,8.17; 2,11.19; 3,4.5.6.11; 4,11; 1 Samuel 1,7.23; 2,14.19.22.23.35; 3,11.17.18; 5,87; 6,2,5,7,9,10; 8,8.12.16; 10,2.7.8; 11,7.10.13; 12,6.7.16.17.20.22; 13,11.19; 14,6.7.36.40.44.44.45.48; 15,2.6.19; 16,3.4; 17,25.26.27.29; 19,5.18; 20,1.2.4.8.13.14.32; 22,3; 24,5.7.19.20; 25,17.18.22.28.30; 26,16.18.25. </span>"
    },
    {
      "ref_id": "fn16-20399",
      "number": 16,
      "text": "“Sobem” (‘lh). Cf. Gênesis 2,6; Josué 15,3.6.7.8.15; 16,1; 17.15; 18,11.12; 19,10.11.12.47; 22,12.23.26.27.28.29.33; 24,17.32; Juízes 1,1.2.3.4.16.22; 2,1; 4,5.10.12; 6,3.5.8.13.21.26.28.35; 8,8.11; 9,48.51; 11,13.16.31; 12,3; 13,5.16.19.20.23; 14,2.19; 15,6.9.10.13; 16,3.5.8.17.18.31; 18,9.12.17; 19,25.30; 20,3.18.23.26.28.30.31.38.40; 21,4.5.8.19; Rute 4,1; 1 Samuel 1,3.7.11.21.22.24; 2,6.14.19.28; 5,12; 6,7.9.14.15.20.21; 7,1,7,9,10; 8,8; 9,11.13.14.19.26; 10,3.8.18; 11,1; 12,6; 13,5.9.10.12.15; 14,9.10.12.13.21.46; 15,2.6.22.34; 17,23.25; 19,15; 23,19; 24,1.23; 25,5.13.35; 27,8; 28,8.11.13.14.15; 29,9.11.",
      "raw_html": "<span>“Sobem” (<em>‘lh</em>). Cf. Gênesis 2,6; Josué 15,3.6.7.8.15; 16,1; 17.15; 18,11.12; 19,10.11.12.47; 22,12.23.26.27.28.29.33; 24,17.32; Juízes 1,1.2.3.4.16.22; 2,1; 4,5.10.12; 6,3.5.8.13.21.26.28.35; 8,8.11; 9,48.51; 11,13.16.31; 12,3; 13,5.16.19.20.23; 14,2.19; 15,6.9.10.13; 16,3.5.8.17.18.31; 18,9.12.17; 19,25.30; 20,3.18.23.26.28.30.31.38.40; 21,4.5.8.19; Rute 4,1; 1 Samuel 1,3.7.11.21.22.24; 2,6.14.19.28; 5,12; 6,7.9.14.15.20.21; 7,1,7,9,10; 8,8; 9,11.13.14.19.26; 10,3.8.18; 11,1; 12,6; 13,5.9.10.12.15; 14,9.10.12.13.21.46; 15,2.6.22.34; 17,23.25; 19,15; 23,19; 24,1.23; 25,5.13.35; 27,8; 28,8.11.13.14.15; 29,9.11. </span>"
    },
    {
      "ref_id": "fn17-20399",
      "number": 17,
      "text": "“E ardem eles” (wayyishrepu).",
      "raw_html": "<span>“<a data-id=\"https://nossabiblialivre.com/referencias/#AAAAO\" data-type=\"link\" href=\"https://nossabiblialivre.com/referencias/#AAAAO\" rel=\"noreferrer noopener\" target=\"_blank\">E ardem eles</a>” (<em>wayyishrepu</em>). </span>"
    },
    {
      "ref_id": "fn18-20399",
      "number": 18,
      "text": "“Na flama” (ba’esh).",
      "raw_html": "<span>“<a data-id=\"https://nossabiblialivre.com/referencias/#AAAAQ\" data-type=\"link\" href=\"https://nossabiblialivre.com/referencias/#AAAAQ\" rel=\"noreferrer noopener\" target=\"_blank\">Na flama</a>” (<em>ba’esh</em>). </span>"
    },
    {
      "ref_id": "fn19-20399",
      "number": 19,
      "text": "“Fazeis vós” (‘sh). Cf. Gênesis 1,7; Josué 22,5.23.24.26.28; 23,3.6.8; 24,5.7.17.31; Juízes 1,7.24; 2,2.7.10.11; 3,7.12.16; 5,1; 6,1.2.17.19.20.27.29.40; 7,17; 8,1.2.3.27.35; 9,16.19.27.33.48.56; 10,6.15; 11,10.27.36.37.39; 13,1.8.15.16.19; 14,6.10; 15,3.6.7.10.11; 16,11; 17,3.4.5.6.8; 18,3.4.14.18.24.27.31; 19,23.24; 20,6.9.10; 21,7.11.15.16.23.25; Rute 1,8.17; 2,11.19; 3,4.5.6.11; 4,11; 1 Samuel 1,7.23; 2,14.19.22.23.35; 3,11.17.18; 5,87; 6,2,5,7,9,10; 8,8.12.16; 10,2.7.8; 11,7.10.13; 12,6.7.16.17.20.22; 13,11.19; 14,6.7.36.40.44.44.45.48; 15,2.6.19; 16,3.4; 17,25.26.27.29; 19,5.18; 20,1.2.4.8.13.14.32; 22,3; 24,5.7.19.20; 25,17.18.22.28.30; 26,16.18.25.",
      "raw_html": "<span>“Fazeis vós” (<em>‘sh</em>). Cf. Gênesis 1,7; Josué 22,5.23.24.26.28; 23,3.6.8; 24,5.7.17.31; Juízes 1,7.24; 2,2.7.10.11; 3,7.12.16; 5,1; 6,1.2.17.19.20.27.29.40; 7,17; <mark class=\"has-inline-color has-black-color\" style=\"background-color:rgba(0, 0, 0, 0)\">8,1.2.3.27.35</mark>; 9,16.19.27.33.48.56; 10,6.15; 11,10.27.36.37.39; 13,1.8.15.16.19; 14,6.10; 15,3.6.7.10.11; 16,11; 17,3.4.5.6.8; 18,3.4.14.18.24.27.31; 19,23.24; 20,6.9.10; 21,7.11.15.16.23.25; Rute 1,8.17; 2,11.19; 3,4.5.6.11; 4,11; 1 Samuel 1,7.23; 2,14.19.22.23.35; 3,11.17.18; 5,87; 6,2,5,7,9,10; 8,8.12.16; 10,2.7.8; 11,7.10.13; 12,6.7.16.17.20.22; 13,11.19; 14,6.7.36.40.44.44.45.48; 15,2.6.19; 16,3.4; 17,25.26.27.29; 19,5.18; 20,1.2.4.8.13.14.32; 22,3; 24,5.7.19.20; 25,17.18.22.28.30; 26,16.18.25. </span>"
    },
    {
      "ref_id": "fn20-20399",
      "number": 20,
      "text": "“Que sim” (ki ‘im). Cf. Gênesis 15,4; Josué 14,4; 17,3; 23,8.12; Juízes 15,7; Rute 3,12.18; 1 Samuel 2,15; 8,19; 14,39; 20,9; 21,5.6.7; 25,34; 26,10; 30,17.22.",
      "raw_html": "<span>“Que sim” (<em>ki ‘im</em>). Cf. Gênesis 15,4; Josué 14,4; 17,3; 23,8.12; Juízes 15,7; Rute 3,12.18; 1 Samuel 2,15; 8,19; 14,39; 20,9; 21,5.6.7; 25,34; 26,10; 30,17.22. </span>"
    },
    {
      "ref_id": "fn21-20399",
      "number": 21,
      "text": "“Faz ele ferir” (nkh). Forma causativa da raiz.",
      "raw_html": "<span>“<a data-id=\"https://nossabiblialivre.com/referencias/#AAAAN\" data-type=\"link\" href=\"https://nossabiblialivre.com/referencias/#AAAAN\" rel=\"noreferrer noopener\" target=\"_blank\">Faz ele ferir</a>” (<em>nkh</em>). Forma causativa da raiz. </span>"
    },
    {
      "ref_id": "fn22-20399",
      "number": 22,
      "text": "“Eles” (‘otam).",
      "raw_html": "<span>“<a data-id=\"https://nossabiblialivre.com/referencias/#AAAGA\" data-type=\"link\" href=\"https://nossabiblialivre.com/referencias/#AAAGA\" rel=\"noreferrer noopener\" target=\"_blank\">Eles</a>” (<em>‘otam</em>). </span>"
    },
    {
      "ref_id": "fn23-20399",
      "number": 23,
      "text": "“Calamidade grande” (makkah gedolah). Cf. Josué 10,10.20; Juízes 11,33; 15,8; 1 Samuel 6,19; 19,8; 23,5.",
      "raw_html": "<span>“Calamidade grande” (<em>makkah gedolah</em>). Cf. Josué 10,10.20; Juízes 11,33; 15,8; 1 Samuel 6,19; 19,8; 23,5. </span>"
    },
    {
      "ref_id": "fn24-20399",
      "number": 24,
      "text": "“Sobem” (‘lh). Cf. Gênesis 2,6; Josué 15,3.6.7.8.15; 16,1; 17.15; 18,11.12; 19,10.11.12.47; 22,12.23.26.27.28.29.33; 24,17.32; Juízes 1,1.2.3.4.16.22; 2,1; 4,5.10.12; 6,3.5.8.13.21.26.28.35; 8,8.11; 9,48.51; 11,13.16.31; 12,3; 13,5.16.19.20.23; 14,2.19; 15,6.9.10.13; 16,3.5.8.17.18.31; 18,9.12.17; 19,25.30; 20,3.18.23.26.28.30.31.38.40; 21,4.5.8.19; Rute 4,1; 1 Samuel 1,3.7.11.21.22.24; 2,6.14.19.28; 5,12; 6,7.9.14.15.20.21; 7,1,7,9,10; 8,8; 9,11.13.14.19.26; 10,3.8.18; 11,1; 12,6; 13,5.9.10.12.15; 14,9.10.12.13.21.46; 15,2.6.22.34; 17,23.25; 19,15; 23,19; 24,1.23; 25,5.13.35; 27,8; 28,8.11.13.14.15; 29,9.11.",
      "raw_html": "<span>“Sobem” (<em>‘lh</em>). Cf. Gênesis 2,6; Josué 15,3.6.7.8.15; 16,1; 17.15; 18,11.12; 19,10.11.12.47; 22,12.23.26.27.28.29.33; 24,17.32; Juízes 1,1.2.3.4.16.22; 2,1; 4,5.10.12; 6,3.5.8.13.21.26.28.35; 8,8.11; 9,48.51; 11,13.16.31; 12,3; 13,5.16.19.20.23; 14,2.19; 15,6.9.10.13; 16,3.5.8.17.18.31; 18,9.12.17; 19,25.30; 20,3.18.23.26.28.30.31.38.40; 21,4.5.8.19; Rute 4,1; 1 Samuel 1,3.7.11.21.22.24; 2,6.14.19.28; 5,12; 6,7.9.14.15.20.21; 7,1,7,9,10; 8,8; 9,11.13.14.19.26; 10,3.8.18; 11,1; 12,6; 13,5.9.10.12.15; 14,9.10.12.13.21.46; 15,2.6.22.34; 17,23.25; 19,15; 23,19; 24,1.23; 25,5.13.35; 27,8; 28,8.11.13.14.15; 29,9.11. </span>"
    },
    {
      "ref_id": "fn25-20399",
      "number": 25,
      "text": "“Acampam eles” (hnh). Cf. Gênesis 26,17; Josué 4,19; 5,10; 8,11; 10,5.31.34; 11,5; Juízes 6,4.33; 7,1; 9,50; 10,17; 11,18.20; 15,9; 18,12; 19,9; 20,19; 1 Samuel 4,1; 11,1; 13,5.16; 17,1.2; 216,3.",
      "raw_html": "<span>“Acampam eles” (<em>hnh</em>). Cf. Gênesis 26,17; Josué 4,19; 5,10; 8,11; 10,5.31.34; 11,5; Juízes 6,4.33; 7,1; 9,50; 10,17; 11,18.20; 15,9; 18,12; 19,9; 20,19; 1 Samuel 4,1; 11,1; 13,5.16; 17,1.2; 216,3. </span>"
    },
    {
      "ref_id": "fn26-20399",
      "number": 26,
      "text": "“Subis vós” (‘lh). Cf. Gênesis 2,6; Josué 15,3.6.7.8.15; 16,1; 17.15; 18,11.12; 19,10.11.12.47; 22,12.23.26.27.28.29.33; 24,17.32; Juízes 1,1.2.3.4.16.22; 2,1; 4,5.10.12; 6,3.5.8.13.21.26.28.35; 8,8.11; 9,48.51; 11,13.16.31; 12,3; 13,5.16.19.20.23; 14,2.19; 15,6.9.10.13; 16,3.5.8.17.18.31; 18,9.12.17; 19,25.30; 20,3.18.23.26.28.30.31.38.40; 21,4.5.8.19; Rute 4,1; 1 Samuel 1,3.7.11.21.22.24; 2,6.14.19.28; 5,12; 6,7.9.14.15.20.21; 7,1,7,9,10; 8,8; 9,11.13.14.19.26; 10,3.8.18; 11,1; 12,6; 13,5.9.10.12.15; 14,9.10.12.13.21.46; 15,2.6.22.34; 17,23.25; 19,15; 23,19; 24,1.23; 25,5.13.35; 27,8; 28,8.11.13.14.15; 29,9.11.",
      "raw_html": "<span>“Subis vós” (<em>‘lh</em>). Cf. Gênesis 2,6; Josué 15,3.6.7.8.15; 16,1; 17.15; 18,11.12; 19,10.11.12.47; 22,12.23.26.27.28.29.33; 24,17.32; Juízes 1,1.2.3.4.16.22; 2,1; 4,5.10.12; 6,3.5.8.13.21.26.28.35; 8,8.11; 9,48.51; 11,13.16.31; 12,3; 13,5.16.19.20.23; 14,2.19; 15,6.9.10.13; 16,3.5.8.17.18.31; 18,9.12.17; 19,25.30; 20,3.18.23.26.28.30.31.38.40; 21,4.5.8.19; Rute 4,1; 1 Samuel 1,3.7.11.21.22.24; 2,6.14.19.28; 5,12; 6,7.9.14.15.20.21; 7,1,7,9,10; 8,8; 9,11.13.14.19.26; 10,3.8.18; 11,1; 12,6; 13,5.9.10.12.15; 14,9.10.12.13.21.46; 15,2.6.22.34; 17,23.25; 19,15; 23,19; 24,1.23; 25,5.13.35; 27,8; 28,8.11.13.14.15; 29,9.11. </span>"
    },
    {
      "ref_id": "fn27-20399",
      "number": 27,
      "text": "“Subimos nós” (‘lh). Cf. acima.",
      "raw_html": "<span>“Subimos nós” (<em>‘lh</em>). Cf. acima. </span>"
    },
    {
      "ref_id": "fn28-20399",
      "number": 28,
      "text": "“Fazer” (‘sh). Forma infinitiva da raiz. Cf. Gênesis 1,7; Josué 22,5.23.24.26.28; 23,3.6.8; 24,5.7.17.31; Juízes 1,7.24; 2,2.7.10.11; 3,7.12.16; 5,1; 6,1.2.17.19.20.27.29.40; 7,17; 8,1.2.3.27.35; 9,16.19.27.33.48.56; 10,6.15; 11,10.27.36.37.39; 13,1.8.15.16.19; 14,6.10; 15,3.6.7.10.11; 16,11; 17,3.4.5.6.8; 18,3.4.14.18.24.27.31; 19,23.24; 20,6.9.10; 21,7.11.15.16.23.25; Rute 1,8.17; 2,11.19; 3,4.5.6.11; 4,11; 1 Samuel 1,7.23; 2,14.19.22.23.35; 3,11.17.18; 5,87; 6,2,5,7,9,10; 8,8.12.16; 10,2.7.8; 11,7.10.13; 12,6.7.16.17.20.22; 13,11.19; 14,6.7.36.40.44.44.45.48; 15,2.6.19; 16,3.4; 17,25.26.27.29; 19,5.18; 20,1.2.4.8.13.14.32; 22,3; 24,5.7.19.20; 25,17.18.22.28.30; 26,16.18.25.",
      "raw_html": "<span>“Fazer” (<em>‘sh</em>). Forma infinitiva da raiz. Cf. Gênesis 1,7; Josué 22,5.23.24.26.28; 23,3.6.8; 24,5.7.17.31; Juízes 1,7.24; 2,2.7.10.11; 3,7.12.16; 5,1; 6,1.2.17.19.20.27.29.40; 7,17; <mark class=\"has-inline-color has-black-color\" style=\"background-color:rgba(0, 0, 0, 0)\">8,1.2.3.27.35</mark>; 9,16.19.27.33.48.56; 10,6.15; 11,10.27.36.37.39; 13,1.8.15.16.19; 14,6.10; 15,3.6.7.10.11; 16,11; 17,3.4.5.6.8; 18,3.4.14.18.24.27.31; 19,23.24; 20,6.9.10; 21,7.11.15.16.23.25; Rute 1,8.17; 2,11.19; 3,4.5.6.11; 4,11; 1 Samuel 1,7.23; 2,14.19.22.23.35; 3,11.17.18; 5,87; 6,2,5,7,9,10; 8,8.12.16; 10,2.7.8; 11,7.10.13; 12,6.7.16.17.20.22; 13,11.19; 14,6.7.36.40.44.44.45.48; 15,2.6.19; 16,3.4; 17,25.26.27.29; 19,5.18; 20,1.2.4.8.13.14.32; 22,3; 24,5.7.19.20; 25,17.18.22.28.30; 26,16.18.25. </span>"
    },
    {
      "ref_id": "fn29-20399",
      "number": 29,
      "text": "“Faz ele” (‘sh). Cf. acima.",
      "raw_html": "<span>“Faz ele” (<em>‘sh</em>). Cf. acima. </span>"
    },
    {
      "ref_id": "fn30-20399",
      "number": 30,
      "text": "“Três de” (sheloshet). Cf. Gênesis 30,36; Josué 1,11; 2,16.22; 3,2; 9,16; 17,11; Juízes 7,20; 14,14; 15,11; 19,4; 1 Samuel 9,20; 10,3; 13,2; 17,13; 20,20; 24,3; 25,2; 26,2; 31,8.",
      "raw_html": "<span>“Três de” (<em>sheloshet</em>). Cf. Gênesis 30,36; Josué 1,11; 2,16.22; 3,2; 9,16; 17,11; Juízes 7,20; 14,14; 15,11; 19,4; 1 Samuel 9,20; 10,3; 13,2; 17,13; 20,20; 24,3; 25,2; 26,2; 31,8. </span>"
    },
    {
      "ref_id": "fn31-20399",
      "number": 31,
      "text": "“Três de milhares” (shelshet ‘alapim). Cf. Números 4,44; Juízes 15,11; 1 Samuel 13,2; 24,3; 25,2; 26,2.",
      "raw_html": "<span>“Três de milhares” (<em>shelshet ‘alapim</em>). Cf. Números 4,44; Juízes 15,11; 1 Samuel 13,2; 24,3; 25,2; 26,2. </span>"
    },
    {
      "ref_id": "fn32-20399",
      "number": 32,
      "text": "“Milhares” (‘alapim). Cf. Êxodo 18,21; Josué 7,3.4; 8,12; Juízes 1,4; 3,29; 4,6.14; 7,3; 15,11; 16,27; 20,34.45; 1 Samuel 4,2; 8,12; 13,2.5; 15,4; 17,5; 22,7; 24,3; 25,2; 26,2.",
      "raw_html": "<span>“Milhares” (<em>‘alapim</em>). Cf. Êxodo 18,21; Josué 7,3.4; 8,12; Juízes 1,4; 3,29; 4,6.14; 7,3; 15,11; 16,27; 20,34.45; 1 Samuel 4,2; 8,12; 13,2.5; 15,4; 17,5; 22,7; 24,3; 25,2; 26,2. </span>"
    },
    {
      "ref_id": "fn33-20399",
      "number": 33,
      "text": "“Três de milhares. Homem” (shelshet ‘alapim ‘ish). Somente em Juízes 15,11; 1 Samuel 24,3; 26,2.",
      "raw_html": "<span>“Três de milhares. Homem” (<em>shelshet ‘alapim ‘ish</em>). Somente em Juízes 15,11; 1 Samuel 24,3; 26,2. </span>"
    },
    {
      "ref_id": "fn34-20399",
      "number": 34,
      "text": "“Governadores” (mshl). Forma participial da raiz.",
      "raw_html": "<span>“<a data-id=\"https://nossabiblialivre.com/referencias/00000025\" data-type=\"link\" href=\"https://nossabiblialivre.com/referencias/00000025\">Governadores</a>” (<em>mshl</em>). Forma participial da raiz. </span>"
    },
    {
      "ref_id": "fn35-20399",
      "number": 35,
      "text": "“Governadores” (moshlim).",
      "raw_html": "<span>“<a data-id=\"https://nossabiblialivre.com/referencias/#00000024\" data-type=\"link\" href=\"https://nossabiblialivre.com/referencias/#00000024\" rel=\"noopener\" target=\"_blank\">Governadores</a>” (<em>moshlim</em>). </span>"
    },
    {
      "ref_id": "fn36-20399",
      "number": 36,
      "text": "“E qual” (umah). Cf. Gênesis 20,9; Juízes 8,3; 14,18; 15,11; 18,3.24; 1 Samuel 9,7; 15,14; 20,1; 26,18.",
      "raw_html": "<span>“E qual” (<em>umah</em>). Cf. Gênesis 20,9; Juízes 8,3; 14,18; 15,11; 18,3.24; 1 Samuel 9,7; 15,14; 20,1; 26,18. </span>"
    },
    {
      "ref_id": "fn37-20399",
      "number": 37,
      "text": "“Fazes tu” (‘sh). Cf. Gênesis 1,7; Josué 22,5.23.24.26.28; 23,3.6.8; 24,5.7.17.31; Juízes 1,7.24; 2,2.7.10.11; 3,7.12.16; 5,1; 6,1.2.17.19.20.27.29.40; 7,17; 8,1.2.3.27.35; 9,16.19.27.33.48.56; 10,6.15; 11,10.27.36.37.39; 13,1.8.15.16.19; 14,6.10; 15,3.6.7.10.11; 16,11; 17,3.4.5.6.8; 18,3.4.14.18.24.27.31; 19,23.24; 20,6.9.10; 21,7.11.15.16.23.25; Rute 1,8.17; 2,11.19; 3,4.5.6.11; 4,11; 1 Samuel 1,7.23; 2,14.19.22.23.35; 3,11.17.18; 5,87; 6,2,5,7,9,10; 8,8.12.16; 10,2.7.8; 11,7.10.13; 12,6.7.16.17.20.22; 13,11.19; 14,6.7.36.40.44.44.45.48; 15,2.6.19; 16,3.4; 17,25.26.27.29; 19,5.18; 20,1.2.4.8.13.14.32; 22,3; 24,5.7.19.20; 25,17.18.22.28.30; 26,16.18.25.",
      "raw_html": "<span>“Fazes tu” (<em>‘sh</em>). Cf. Gênesis 1,7; Josué 22,5.23.24.26.28; 23,3.6.8; 24,5.7.17.31; Juízes 1,7.24; 2,2.7.10.11; 3,7.12.16; 5,1; 6,1.2.17.19.20.27.29.40; 7,17; <mark class=\"has-inline-color has-black-color\" style=\"background-color:rgba(0, 0, 0, 0)\">8,1.2.3.27.35</mark>; 9,16.19.27.33.48.56; 10,6.15; 11,10.27.36.37.39; 13,1.8.15.16.19; 14,6.10; 15,3.6.7.10.11; 16,11; 17,3.4.5.6.8; 18,3.4.14.18.24.27.31; 19,23.24; 20,6.9.10; 21,7.11.15.16.23.25; Rute 1,8.17; 2,11.19; 3,4.5.6.11; 4,11; 1 Samuel 1,7.23; 2,14.19.22.23.35; 3,11.17.18; 5,87; 6,2,5,7,9,10; 8,8.12.16; 10,2.7.8; 11,7.10.13; 12,6.7.16.17.20.22; 13,11.19; 14,6.7.36.40.44.44.45.48; 15,2.6.19; 16,3.4; 17,25.26.27.29; 19,5.18; 20,1.2.4.8.13.14.32; 22,3; 24,5.7.19.20; 25,17.18.22.28.30; 26,16.18.25. </span>"
    },
    {
      "ref_id": "fn38-20399",
      "number": 38,
      "text": "“Fazem eles” (‘sh). Cf. acima.",
      "raw_html": "<span>“Fazem eles” (<em>‘sh</em>). Cf. acima. </span>"
    },
    {
      "ref_id": "fn39-20399",
      "number": 39,
      "text": "“Faço eu” (‘sh). Cf. acima.",
      "raw_html": "<span>“Faço eu” (<em>‘sh</em>). Cf. acima. </span>"
    },
    {
      "ref_id": "fn40-20399",
      "number": 40,
      "text": "“Em mão de” (beyad). Cf. Gênesis 27,17; Josué 7,7; 10,30.32; 11,8; 14,2; 20,2.9; 21,2.8; 22,9; Juízes 2,14.23; 3,4.8; 4,2.9; 6,1; 7,16.20; 10,7; 11,21; 13,1; 15,12.18; 11,7; 12,9; 13,22; 14,12.37; 16,20; 17,50; 18,10.25; 19,9; 23,12.20; 26,23; 27,1; 28,15.19; 30,15.",
      "raw_html": "<span>“Em mão de” (<em>beyad</em>). Cf. Gênesis 27,17; Josué 7,7; 10,30.32; 11,8; 14,2; 20,2.9; 21,2.8; 22,9; Juízes 2,14.23; 3,4.8; 4,2.9; 6,1; 7,16.20; 10,7; 11,21; 13,1; 15,12.18; 11,7; 12,9; 13,22; 14,12.37; 16,20; 17,50; 18,10.25; 19,9; 23,12.20; 26,23; 27,1; 28,15.19; 30,15. </span>"
    },
    {
      "ref_id": "fn41-20399",
      "number": 41,
      "text": "“Fazer morrer” (mwt). Forma causativa infinitiva da raiz.",
      "raw_html": "<span>“<a data-id=\"https://nossabiblialivre.com/referencias/#AAABC\" data-type=\"link\" href=\"https://nossabiblialivre.com/referencias/#AAABC\" rel=\"noreferrer noopener\" target=\"_blank\">Fazer morrer</a>” (<em>mwt</em>). Forma causativa infinitiva da raiz. </span>"
    },
    {
      "ref_id": "fn42-20399",
      "number": 42,
      "text": "“Fazemos nós morrer” (mwt). Forma causativa da raiz.",
      "raw_html": "<span>“<a data-id=\"https://nossabiblialivre.com/referencias/#AAABC\" data-type=\"link\" href=\"https://nossabiblialivre.com/referencias/#AAABC\" rel=\"noreferrer noopener\" target=\"_blank\">Fazemos nós morrer</a>” (<em>mwt</em>). Forma causativa da raiz. </span>"
    },
    {
      "ref_id": "fn43-20399",
      "number": 43,
      "text": "“Fazem eles subir” (‘lh). Cf. Gênesis 2,6; Josué 15,3.6.7.8.15; 16,1; 17.15; 18,11.12; 19,10.11.12.47; 22,12.23.26.27.28.29.33; 24,17.32; Juízes 1,1.2.3.4.16.22; 2,1; 4,5.10.12; 6,3.5.8.13.21.26.28.35; 8,8.11; 9,48.51; 11,13.16.31; 12,3; 13,5.16.19.20.23; 14,2.19; 15,6.9.10.13; 16,3.5.8.17.18.31; 18,9.12.17; 19,25.30; 20,3.18.23.26.28.30.31.38.40; 21,4.5.8.19; Rute 4,1; 1 Samuel 1,3.7.11.21.22.24; 2,6.14.19.28; 5,12; 6,7.9.14.15.20.21; 7,1,7,9,10; 8,8; 9,11.13.14.19.26; 10,3.8.18; 11,1; 12,6; 13,5.9.10.12.15; 14,9.10.12.13.21.46; 15,2.6.22.34; 17,23.25; 19,15; 23,19; 24,1.23; 25,5.13.35; 27,8; 28,8.11.13.14.15; 29,9.11.",
      "raw_html": "<span>“Fazem eles subir” (<em>‘lh</em>). Cf. Gênesis 2,6; Josué 15,3.6.7.8.15; 16,1; 17.15; 18,11.12; 19,10.11.12.47; 22,12.23.26.27.28.29.33; 24,17.32; Juízes 1,1.2.3.4.16.22; 2,1; 4,5.10.12; 6,3.5.8.13.21.26.28.35; 8,8.11; 9,48.51; 11,13.16.31; 12,3; 13,5.16.19.20.23; 14,2.19; 15,6.9.10.13; 16,3.5.8.17.18.31; 18,9.12.17; 19,25.30; 20,3.18.23.26.28.30.31.38.40; 21,4.5.8.19; Rute 4,1; 1 Samuel 1,3.7.11.21.22.24; 2,6.14.19.28; 5,12; 6,7.9.14.15.20.21; 7,1,7,9,10; 8,8; 9,11.13.14.19.26; 10,3.8.18; 11,1; 12,6; 13,5.9.10.12.15; 14,9.10.12.13.21.46; 15,2.6.22.34; 17,23.25; 19,15; 23,19; 24,1.23; 25,5.13.35; 27,8; 28,8.11.13.14.15; 29,9.11. </span>"
    },
    {
      "ref_id": "fn44-20399",
      "number": 44,
      "text": "“Idor” (bw’). Forma participial da raiz. Cf. Gênesis 2,19; Josué 10,9.13.19.20.27; 11,5.7.21; 13,1; 14,11; 15,18; 18,3.4.6.9; 20,6; 21,45; 22,10.15; 23,1.2.7.12.14.15; 24,6.7.8.11; Juízes 1,7.14; 2,1; 3,20.22.24.27; 4,20.21.22; 5,19.23.28; 6,4.5.11.18.19; 7,13.17.19.25; 8,4.15; 9,5.15.24.26.27.31.37.46.52.57; 11,7.12.16.18.33.34; 12,9; 13,6.8.9.11.12.17; 14,5.18; 15,1.14; 16,1.2; 17,8.9; 18,2.3.7.8.9.10.13.15.17.18.20.27; 19,3.10.14.15.16.17.21.22.23.26.29; 20,4.10.26.34; 21,2.8.12; 1 Samuel 1,19.22.24.25; 2,13.14.15.27.31.34.36; 3,10; 4,3.5.6.7.12.13.14.16; 5,1.2.5.10; 6,14; 7,1.13; 8,4; 9,5.6.7.12.13.14.15.16.22; 10,3.5.7.8.9.10.13.14.22.27; 11,4,5,9,11; 12,8.12; 13,8.10.11; 14,20.25.26; 15,5.12.13.15.20; 16,2.4.5.6.11.12.17.21; 17,12,18.20.34.43.45.52.54.57; 18,6.13.16.27; 9,7.16.18.22.23; 20,1.8.9.19.21.27.29.37.38.40.41; 21,1.2.11.15.16; 22,5.9.11; 23,7.10.27.27; 24,4; 25,5.8.9.12.19.26.27.33.34.35.36.40; 26,1.3.4.5.7.10.15.",
      "raw_html": "<span>“Idor” (<em>bw’</em>). Forma participial da raiz. Cf. Gênesis 2,19; Josué 10,9.13.19.20.27; 11,5.7.21; 13,1; 14,11; 15,18; 18,3.4.6.9; 20,6; 21,45; 22,10.15; 23,1.2.7.12.14.15; 24,6.7.8.11; Juízes 1,7.14; 2,1; 3,20.22.24.27; 4,20.21.22; 5,19.23.28; 6,4.5.11.18.19; 7,13.17.19.25; 8,4.15; 9,5.15.24.26.27.31.37.46.52.57; 11,7.12.16.18.33.34; 12,9; 13,6.8.9.11.12.17; 14,5.18; 15,1.14; 16,1.2; 17,8.9; 18,2.3.7.8.9.10.13.15.17.18.20.27; 19,3.10.14.15.16.17.21.22.23.26.29; 20,4.10.26.34; 21,2.8.12; 1 Samuel 1,19.22.24.25; 2,13.14.15.27.31.34.36; 3,10; 4,3.5.6.7.12.13.14.16; 5,1.2.5.10; 6,14; 7,1.13; 8,4; 9,5.6.7.12.13.14.15.16.22; 10,3.5.7.8.9.10.13.14.22.27; 11,4,5,9,11; 12,8.12; 13,8.10.11; 14,20.25.26; 15,5.12.13.15.20; 16,2.4.5.6.11.12.17.21; 17,12,18.20.34.43.45.52.54.57; 18,6.13.16.27; 9,7.16.18.22.23; 20,1.8.9.19.21.27.29.37.38.40.41; 21,1.2.11.15.16; 22,5.9.11; 23,7.10.27.27; 24,4; 25,5.8.9.12.19.26.27.33.34.35.36.40; 26,1.3.4.5.7.10.15. </span>"
    },
    {
      "ref_id": "fn45-20399",
      "number": 45,
      "text": "“Estão elas” (hyh).",
      "raw_html": "<span>“<a data-id=\"https://nossabiblialivre.com/referencias/#AAAAB\" data-type=\"link\" href=\"https://nossabiblialivre.com/referencias/#AAAAB\" rel=\"noopener\" target=\"_blank\">Estão elas</a>” (<em>hyh</em>). </span>"
    },
    {
      "ref_id": "fn46-20399",
      "number": 46,
      "text": "“Cordoamentações [“cordoamentos]” (‘abotim). O termo apareceu no verso anterior, e foi tratado, lá, pelo narrador, como masculino. Aqui, o termo é tratado, pelo narrador, como feminino (daí a forma verbal “estão elas” imediatamente acima). Os léxicos dão o termo como de dois gêneros. Mas encontrar, na mesma passagem, o uso do termo, aqui, como feminino, e ali como masculino, é realmente surpreendente. O redator não é muito hábil com sua gramática? Ou estamos diante de corrupção ou acréscimos, tão comuns no Tanak?",
      "raw_html": "<span>“Cordoamentações [“cordoamentos]” (<em>‘abotim</em>). O termo apareceu no verso anterior, e foi tratado, lá, pelo narrador, como masculino. Aqui, o termo é tratado, pelo narrador, como feminino (daí a forma verbal “estão elas” imediatamente acima). Os léxicos dão o termo como de dois gêneros. Mas encontrar, na mesma passagem, o uso do termo, aqui, como feminino, e ali como masculino, é realmente surpreendente. O redator não é muito hábil com sua gramática? Ou estamos diante de corrupção ou acréscimos, tão comuns no Tanak? </span>"
    },
    {
      "ref_id": "fn47-20399",
      "number": 47,
      "text": "“Na flama” (ba’esh).",
      "raw_html": "<span>“<a data-id=\"https://nossabiblialivre.com/referencias/#AAAAQ\" data-type=\"link\" href=\"https://nossabiblialivre.com/referencias/#AAAAQ\" rel=\"noreferrer noopener\" target=\"_blank\">Na flama</a>” (<em>ba’esh</em>). </span>"
    },
    {
      "ref_id": "fn48-20399",
      "number": 48,
      "text": "“As mãos dele” (yadayw).",
      "raw_html": "<span>“<a data-id=\"https://nossabiblialivre.com/referencias/#AAABG\" data-type=\"link\" href=\"https://nossabiblialivre.com/referencias/#AAABG\" rel=\"noreferrer noopener\" target=\"_blank\">As mãos dele</a>” (<em>yadayw</em>). </span>"
    },
    {
      "ref_id": "fn49-20399",
      "number": 49,
      "text": "“E envia ele” (wayyishlah).",
      "raw_html": "<span>“<a data-id=\"https://nossabiblialivre.com/referencias/#AAAIG\" data-type=\"link\" href=\"https://nossabiblialivre.com/referencias/#AAAIG\" rel=\"noreferrer noopener\" target=\"_blank\">E envia ele</a>” (<em>wayyishlah</em>). </span>"
    },
    {
      "ref_id": "fn50-20399",
      "number": 50,
      "text": "“Envia ele” (shlh). Cf. Gênesis 3,22; Josué 10,3.6; 11,1; 14,7.11; 18,4; 22,6.7.13; 24,5.9.12.28; Juízes 1,8.25; 2,6; 3,15.18.21; 4,6; 5,15.26; 6,8.14.21.35; 7,8.24; 9,23.31; 11,12.14.17.19.28.38; 12,9; 13,8; 15,5.15; 16,18; 18,2; 19,25.29; 20,6.12.48; 21,10.13; 1 Samuel 4,4; 5,8.10.11; 6,2.3.6.8.21; 9,16.19.26; 10,25; 11,13.7; 12,8.11; 13,2; 14,27; 15,1.18.20; 16,1.11.12.19.20.22; 17,49; 18,5; 19,11.14.15.17.20.21; 20,5.12.13.20.21.22.29.31; 21,3; 22,11.17; 24,7.11.20; 25,5.14.25.32.39.40; 26,4.9.11.23; 30,26; 31,9.",
      "raw_html": "<span>“Envia ele” (<em>shlh</em>). Cf. Gênesis 3,22; Josué 10,3.6; 11,1; 14,7.11; 18,4; 22,6.7.13; 24,5.9.12.28; Juízes 1,8.25; 2,6; 3,15.18.21; 4,6; 5,15.26; 6,8.14.21.35; 7,8.24; 9,23.31; 11,12.14.17.19.28.38; 12,9; 13,8; 15,5.15; 16,18; 18,2; 19,25.29; 20,6.12.48; 21,10.13; 1 Samuel 4,4; 5,8.10.11; 6,2.3.6.8.21; 9,16.19.26; 10,25; 11,13.7; 12,8.11; 13,2; 14,27; 15,1.18.20; 16,1.11.12.19.20.22; 17,49; 18,5; 19,11.14.15.17.20.21; 20,5.12.13.20.21.22.29.31; 21,3; 22,11.17; 24,7.11.20; 25,5.14.25.32.39.40; 26,4.9.11.23; 30,26; 31,9. </span>"
    },
    {
      "ref_id": "fn51-20399",
      "number": 51,
      "text": "“A mão dele” (yado). Cf. Gênesis 3,22; Josué 8,19.26; Juízes 3,10; 15,15; 1 Samuel 5,7; 6,3.5.9; 14,26.27; 17,49; 23,16; 26,9.",
      "raw_html": "<span>“A mão dele” (<em>yado</em>). Cf. Gênesis 3,22; Josué 8,19.26; Juízes 3,10; 15,15; 1 Samuel 5,7; 6,3.5.9; 14,26.27; 17,49; 23,16; 26,9. </span>"
    },
    {
      "ref_id": "fn52-20399",
      "number": 52,
      "text": "“E toma ele ela” (wayyiqqaheha). Cf. Gênesis 8,9; 38,2; Deuteronômio 30,12.13; Juízes 15,15; 19,28; 26,22.",
      "raw_html": "<span>“E toma ele ela” (<em>wayyiqqaheha</em>). Cf. Gênesis 8,9; 38,2; Deuteronômio 30,12.13; Juízes 15,15; 19,28; 26,22. </span>"
    },
    {
      "ref_id": "fn53-20399",
      "number": 53,
      "text": "“Faz ele ferir” (nkh). Forma causativa da raiz.",
      "raw_html": "<span>“<a data-id=\"https://nossabiblialivre.com/referencias/#AAAAN\" data-type=\"link\" href=\"https://nossabiblialivre.com/referencias/#AAAAN\" rel=\"noreferrer noopener\" target=\"_blank\">Faz ele ferir</a>” (<em>nkh</em>). Forma causativa da raiz. </span>"
    },
    {
      "ref_id": "fn54-20399",
      "number": 54,
      "text": "“Faço eu ferir” (nkh). Forma causativa da raiz.",
      "raw_html": "<span>“<a data-id=\"https://nossabiblialivre.com/referencias/#AAAAN\" data-type=\"link\" href=\"https://nossabiblialivre.com/referencias/#AAAAN\" rel=\"noreferrer noopener\" target=\"_blank\">Faço eu ferir</a>” (<em>nkh</em>). Forma causativa da raiz. </span>"
    },
    {
      "ref_id": "fn55-20399",
      "number": 55,
      "text": "“Está” (hyh).",
      "raw_html": "<span>“<a data-id=\"https://nossabiblialivre.com/referencias/#AAAAB\" data-type=\"link\" href=\"https://nossabiblialivre.com/referencias/#AAAAB\" rel=\"noopener\" target=\"_blank\">Está</a>” (<em>hyh</em>). </span>"
    },
    {
      "ref_id": "fn56-20399",
      "number": 56,
      "text": "“E está” (wayehi).",
      "raw_html": "<span>“<a data-id=\"24610\" data-type=\"page\" href=\"https://nossabiblialivre.com/referencias/#AAAAA\" rel=\"noreferrer noopener\" target=\"_blank\">E está</a>” (<em>wayehi</em>). </span>"
    },
    {
      "ref_id": "fn57-20399",
      "number": 57,
      "text": "“Desde a mão dele” (miyyado). Êxodo 32,19; Números 21,26; Josué 24,10; Juízes 15,17; 1 Samuel 27,1.",
      "raw_html": "<span>“Desde a mão dele” (<em>miyyado</em>). Êxodo 32,19; Números 21,26; Josué 24,10; Juízes 15,17; 1 Samuel 27,1. </span>"
    },
    {
      "ref_id": "fn58-20399",
      "number": 58,
      "text": "“Na mão do” (beyad). Cf. Gênesis 27,17; Josué 7,7; 10,30.32; 11,8; 14,2; 20,2.9; 21,2.8; 22,9; Juízes 2,14.23; 3,4.8; 4,2.9; 6,1; 7,16.20; 10,7; 11,21; 13,1; 15,12.18; 11,7; 12,9; 13,22; 14,12.37; 16,20; 17,50; 18,10.25; 19,9; 23,12.20; 26,23; 27,1; 28,15.19; 30,15.",
      "raw_html": "<span>“Na mão do” (<em>beyad</em>). Cf. Gênesis 27,17; Josué 7,7; 10,30.32; 11,8; 14,2; 20,2.9; 21,2.8; 22,9; Juízes 2,14.23; 3,4.8; 4,2.9; 6,1; 7,16.20; 10,7; 11,21; 13,1; 15,12.18; 11,7; 12,9; 13,22; 14,12.37; 16,20; 17,50; 18,10.25; 19,9; 23,12.20; 26,23; 27,1; 28,15.19; 30,15. </span>"
    },
    {
      "ref_id": "fn59-20399",
      "number": 59,
      "text": "“O servo de” (‘ebed). Cf. Gênesis 9,25; Josué 1,1.2.7.13.15; 5,14; 8,31.33; 9,8.9.11.23.24; 10,6; 11,12.15; 12,6; 13,8; 14,7; 18,7; 22,2.4.5.17.29; Juízes 2,8; 3,24; 6,8.27; 15,18; 19,19; 1 Samuel 3,19.10; 8,14.15.16.17; 12,19; 16,15.16.17; 17,8.9.32.34.36.58; 18,5.22.23.24.26.30; 19,1.4.7; 20,7,8; 21,8.12.15; 22,6.7.8.9.14.15.17; 23,10.11; 25,8.10.39.40.41; 26,18.19; 27,5; 27,12; 28,2.7.23.25.",
      "raw_html": "<span>“O servo de” (<em>‘ebed</em>). Cf. Gênesis 9,25; Josué 1,1.2.7.13.15; 5,14; 8,31.33; 9,8.9.11.23.24; 10,6; 11,12.15; 12,6; 13,8; 14,7; 18,7; 22,2.4.5.17.29; Juízes 2,8; 3,24; 6,8.27; 15,18; 19,19; 1 Samuel 3,19.10; 8,14.15.16.17; 12,19; 16,15.16.17; 17,8.9.32.34.36.58; 18,5.22.23.24.26.30; 19,1.4.7; 20,7,8; 21,8.12.15; 22,6.7.8.9.14.15.17; 23,10.11; 25,8.10.39.40.41; 26,18.19; 27,5; 27,12; 28,2.7.23.25. </span>"
    },
    {
      "ref_id": "fn60-20399",
      "number": 60,
      "text": "“E agora” (we’attah). Cf. Josué 9,6.11.12.19.23.25; 13,7; 14,10.12; 22,4; 24,14.23; Juízes 6,13; 7,3; 9,16.32; 11,13.23.25; 13,4.7; 14,2; 15,18; 17,3; 18,14; 20,9.13; 1 Samuel 2,30; 6,7; 8,9; 9,13; 10,19; 12,2.7.10.13.14; 15,1.25; 18,22; 19,2; 20,29.31; 21,4; 23,20; 24,21.22; 25,7.17.26.27; 26,8.11.16.19.20.22; 29,7.10.",
      "raw_html": "<span>“E agora” (<em>we’attah</em>). Cf. Josué 9,6.11.12.19.23.25; 13,7; 14,10.12; 22,4; 24,14.23; Juízes 6,13; 7,3; 9,16.32; 11,13.23.25; 13,4.7; 14,2; 15,18; 17,3; 18,14; 20,9.13; 1 Samuel 2,30; 6,7; 8,9; 9,13; 10,19; 12,2.7.10.13.14; 15,1.25; 18,22; 19,2; 20,29.31; 21,4; 23,20; 24,21.22; 25,7.17.26.27; 26,8.11.16.19.20.22; 29,7.10. </span>"
    },
    {
      "ref_id": "fn61-20399",
      "number": 61,
      "text": "“Agora” (‘attah). Cf. Gênesis 3,22; Josué 22,4; 24,14.23; Juízes 6,13; 7,3; 8,2.6.15; 9,16.32.38; 11,7.8.13.23.25; 13,4.7.12; 14,2; 15,18; 16,10; 17,3.13; 18,14; 20,9.13; Rute 2,7; 3,2.11,12; 1 Samuel 2,16.30; 6,7; 8,5.9; 9,6.12.13; 10,19; 12,2.7.10.13.16; 13,12.13.14; 14,30; 15,1.3.25.30; 17,29; 18,22; 19,2; 20,29.31; 21,4; 23,20; 24,21.22; 25,7.17.26; 26,8.11.16.19.20; 27,1; 29,7.10.",
      "raw_html": "<span>“Agora” (<em>‘attah</em>). Cf. Gênesis 3,22; Josué 22,4; 24,14.23; Juízes 6,13; 7,3; 8,2.6.15; 9,16.32.38; 11,7.8.13.23.25; 13,4.7.12; 14,2; 15,18; 16,10; 17,3.13; 18,14; 20,9.13; Rute 2,7; 3,2.11,12; 1 Samuel 2,16.30; 6,7; 8,5.9; 9,6.12.13; 10,19; 12,2.7.10.13.16; 13,12.13.14; 14,30; 15,1.3.25.30; 17,29; 18,22; 19,2; 20,29.31; 21,4; 23,20; 24,21.22; 25,7.17.26; 26,8.11.16.19.20; 27,1; 29,7.10. </span>"
    },
    {
      "ref_id": "fn62-20399",
      "number": 62,
      "text": "“Morro eu” (mwt).",
      "raw_html": "<span>“<a data-id=\"https://nossabiblialivre.com/referencias/#AAABC\" data-type=\"link\" href=\"https://nossabiblialivre.com/referencias/#AAABC\" rel=\"noreferrer noopener\" target=\"_blank\">Morro eu</a>” (<em>mwt</em>). </span>"
    },
    {
      "ref_id": "fn63-20399",
      "number": 63,
      "text": "“Na mão dos” (beyad). Cf. acima.",
      "raw_html": "<span>“Na mão dos” (<em>beyad</em>). Cf. acima. </span>"
    },
    {
      "ref_id": "fn64-20399",
      "number": 64,
      "text": "“Volta” (shwb). Cf. Gênesis 3,19; Josué 14,7; 18,8; 19,12.27.29.34; 20,6; 22,8.9.16.18.23.29.32; 23,12; 24,20; Juízes 2,19; 3,19; 5,29; 6,18; 7,3.15; 8,9.13.33; 9,56.57; 11,8.9.13.31.35.39; 14,8; 15,19; 17,3.4; 18,26; 19,3.7; 20,48; 21,14; Rute 1,6.7.11.12.15.16.21.22; 2,6; 4,3.15; 1 Samuel 1,19; 3,5.6; 5,3.11; 6,3.4.7.8.16.17.21; 7,3.14; 9,5; 12,3; 14,27; 15,11.25.26.30.31; 17,15.30.53.57; 18,2.6; 23,23.28; 24,2; 25,12.21.39; 26,21.23.25.",
      "raw_html": "<span>“Volta” (<em>shwb</em>). Cf. Gênesis 3,19; Josué 14,7; 18,8; 19,12.27.29.34; 20,6; 22,8.9.16.18.23.29.32; 23,12; 24,20; Juízes 2,19; 3,19; 5,29; 6,18; 7,3.15; 8,9.13.33; 9,56.57; 11,8.9.13.31.35.39; 14,8; 15,19; 17,3.4; 18,26; 19,3.7; 20,48; 21,14; Rute 1,6.7.11.12.15.16.21.22; 2,6; 4,3.15; 1 Samuel 1,19; 3,5.6; 5,3.11; 6,3.4.7.8.16.17.21; 7,3.14; 9,5; 12,3; 14,27; 15,11.25.26.30.31; 17,15.30.53.57; 18,2.6; 23,23.28; 24,2; 25,12.21.39; 26,21.23.25. </span>"
    },
    {
      "ref_id": "fn65-20399",
      "number": 65,
      "text": "“Vive ele” (hyh).",
      "raw_html": "<span>“<a data-id=\"https://nossabiblialivre.com/referencias/#AAAGK\" data-type=\"link\" href=\"https://nossabiblialivre.com/referencias/#AAAGK\" rel=\"noreferrer noopener\" target=\"_blank\">Vive ele</a>” (<em>hyh</em>). </span>"
    },
    {
      "ref_id": "fn66-20399",
      "number": 66,
      "text": "“O nome de” (shem).",
      "raw_html": "<span>“<a data-id=\"https://nossabiblialivre.com/referencias/#AAAKJ\" data-type=\"link\" href=\"https://nossabiblialivre.com/referencias/#AAAKJ\" rel=\"noreferrer noopener\" target=\"_blank\">O nome de</a>” (<em>shem</em>). </span>"
    },
    {
      "ref_id": "fn67-20399",
      "number": 67,
      "text": "“O nome dela” (shemah).",
      "raw_html": "<span>“<a data-id=\"https://nossabiblialivre.com/referencias/#AAAKK\" data-type=\"link\" href=\"https://nossabiblialivre.com/referencias/#AAAKK\" rel=\"noreferrer noopener\" target=\"_blank\">O nome dela</a>” (<em>shemah</em>). </span>"
    },
    {
      "ref_id": "fn68-20399",
      "number": 68,
      "text": "“Até o dia” (‘ad hayyom).",
      "raw_html": "<span>“<a data-id=\"https://nossabiblialivre.com/referencias/#AAACJ\" data-type=\"link\" href=\"https://nossabiblialivre.com/referencias/#AAACJ\" rel=\"noreferrer noopener\" target=\"_blank\">Até o dia</a>” (<em>‘ad hayyom</em>). </span>"
    },
    {
      "ref_id": "fn69-20399",
      "number": 69,
      "text": "“Até o dia esse (‘ad hayyom hazzeh).",
      "raw_html": "<span>“<a data-id=\"https://nossabiblialivre.com/referencias/#AAACH\" data-type=\"link\" href=\"https://nossabiblialivre.com/referencias/#AAACH\" rel=\"noreferrer noopener\" target=\"_blank\">Até o dia esse</a> (<em>‘ad hayyom hazzeh</em>). </span>"
    },
    {
      "ref_id": "fn70-20399",
      "number": 70,
      "text": "“O dia esse” (hayyom hazzeh).",
      "raw_html": "<span>“<a data-id=\"https://nossabiblialivre.com/referencias/#AAACI\" data-type=\"link\" href=\"https://nossabiblialivre.com/referencias/#AAACI\" rel=\"noreferrer noopener\" target=\"_blank\">O dia esse</a>” (<em>hayyom hazzeh</em>). </span>"
    }
  ]
}